<Data><Panels><Panel><Struct name="Singleton"><Component id="0" name="Grid"><Layout name="Center_Single" Number="0" Position="[[0.5, 0.5, 1, 1]]" Uniformity="3"><Entity bbox="[0.5, 0.5, 1, 1]" real_bbox="[0.5, 0.5, 0.7877, 0.7877]" mask="[2657,1,2814,5,2968,1,2971,9,3126,15,3284,18,3438,1,3440,23,3594,30,3752,33,3907,2,3910,36,4064,43,4219,1,4222,46,4377,52,4531,1,4533,57,4689,62,4845,67,5000,2,5003,70,5158,76,5315,80,5474,82,5634,83,5794,84,5953,86,6113,87,6272,89,6432,90,6593,90,6752,92,6912,93,7071,95,7231,96,7391,97,7551,98,7710,100,7870,101,8029,103,8190,103,8349,105,8509,106,8669,107,8829,108,8988,110,9148,111,9307,113,9468,113,9628,114,9787,116,9947,117,10106,119,10266,120,10426,119,10585,120,10745,120,10906,118,11065,119,11225,119,11384,119,11544,119,11703,121,11863,120,12023,120,12183,119,12342,120,12503,118,12662,119,12822,119,12982,119,13142,118,13301,120,13461,119,13620,120,13780,120,13939,121,14100,119,14260,119,14419,119,14579,119,14739,118,14898,120,15058,120,15218,119,15377,120,15538,119,15699,117,15860,116,16021,114,16182,113,16343,113,16504,111,16665,110,16826,108,16987,107,17148,106,17309,105,17470,103,17631,103,17792,101,17953,100,18114,98,18275,97,18436,96,18597,95,18758,93,18919,92,19080,90,19241,90,19402,89,19563,87,19724,86,19885,84,20046,83,20207,82,20368,80,20529,76,20690,70,20761,2,20851,67,21012,62,21173,57,21231,1,21334,52,21495,46,21543,1,21656,43,21817,36,21854,2,21978,33,22139,30,22300,23,22324,1,22461,18,22622,15,22783,9,22794,1,22944,5,23105,1]" Type="4" Size="4" Color="8" Angle="0" /></Layout></Component></Struct></Panel><Panel><Struct name="Singleton"><Component id="0" name="Grid"><Layout name="Center_Single" Number="0" Position="[[0.5, 0.5, 1, 1]]" Uniformity="3"><Entity bbox="[0.5, 0.5, 1, 1]" real_bbox="[0.4845, 0.4845, 0.5712, 0.5712]" mask="[5193,3,5352,6,5511,10,5670,12,5829,15,5988,19,6147,22,6306,24,6465,27,6624,29,6783,33,6942,36,7101,38,7260,42,7419,45,7578,47,7737,50,7896,54,8055,56,8214,59,8373,63,8532,66,8691,68,8760,1,8850,72,9009,75,9168,77,9327,79,9486,80,9645,81,9804,81,9963,82,10122,83,10281,84,10440,85,10599,85,10758,86,10917,88,11076,88,11235,89,11394,89,11553,90,11713,91,11873,91,12034,89,12194,89,12355,88,12515,88,12675,88,12836,86,12997,85,13157,85,13318,84,13478,84,13638,84,13799,82,13959,82,14120,82,14281,81,14441,80,14602,79,14763,77,14923,78,15083,78,15244,76,15404,76,15565,75,15726,74,15886,74,16046,73,16207,72,16367,72,16528,71,16689,71,16849,70,17010,69,17170,68,17330,69,17491,68,17652,67,17812,66,17973,65,18133,65,18293,65,18454,63,18614,62,18775,53,18829,3,18936,45,18985,1,19095,38,19134,2,19256,31,19289,2,19417,24,19577,15,19594,2,19738,9,19749,1,19899,3]" Type="3" Size="2" Color="5" Angle="0" /></Layout></Component></Struct></Panel><Panel><Struct name="Singleton"><Component id="0" name="Grid"><Layout name="Center_Single" Number="0" Position="[[0.5, 0.5, 1, 1]]" Uniformity="3"><Entity bbox="[0.5, 0.5, 1, 1]" real_bbox="[0.5, 0.5, 0.4077, 0.4077]" mask="[7760,3,7919,5,8078,7,8237,9,8396,11,8555,13,8714,15,8873,17,9032,19,9191,21,9350,23,9509,25,9668,27,9827,29,9986,31,10145,33,10304,35,10463,37,10622,39,10781,41,10940,43,11099,45,11258,47,11417,49,11576,51,11735,53,11894,55,12053,57,12212,59,12371,61,12530,63,12689,65,12849,65,13009,65,13170,63,13331,61,13492,59,13653,57,13814,55,13975,53,14136,51,14297,49,14458,47,14619,45,14780,43,14941,41,15102,39,15263,37,15424,35,15585,33,15746,31,15907,29,16068,27,16229,25,16390,23,16551,21,16712,19,16873,17,17034,15,17195,13,17356,11,17517,9,17678,7,17839,5,18000,3]" Type="2" Size="0" Color="3" Angle="0" /></Layout></Component></Struct></Panel><Panel><Struct name="Singleton"><Component id="0" name="Grid"><Layout name="Center_Single" Number="0" Position="[[0.5, 0.5, 1, 1]]" Uniformity="3"><Entity bbox="[0.5, 0.5, 1, 1]" real_bbox="[0.5, 0.5, 0.8188, 0.8188]" mask="[2314,2,2317,2,2320,3,2324,2,2327,1,2469,22,2493,1,2623,1,2625,33,2659,1,2781,41,2939,45,3096,1,3098,47,3146,1,3252,1,3254,55,3310,1,3411,61,3570,63,3728,67,3887,69,4045,73,4204,75,4363,77,4520,1,4522,79,4602,1,4679,85,4838,87,4997,89,5156,91,5315,93,5474,95,5633,97,5792,99,5951,101,6110,103,6269,105,6430,103,6589,105,6748,107,6907,109,7066,111,7226,111,7385,113,7544,115,7704,115,7863,117,8022,119,8183,117,8342,119,8501,121,8661,121,8820,123,8981,121,9140,123,9299,125,9459,125,9618,126,9778,127,9938,127,10098,127,10257,129,10417,129,10577,129,10737,129,10897,129,11056,131,11216,131,11376,131,11536,131,11695,133,11855,133,12016,131,12175,133,12335,133,12496,131,12655,133,12815,133,12975,133,13136,131,13295,133,13455,133,13616,131,13775,133,13936,131,14096,131,14256,131,14417,130,14577,130,14736,131,14897,129,15057,129,15217,129,15377,129,15538,127,15697,129,15858,127,16018,127,16179,125,16339,125,16500,123,16661,121,16820,123,16981,121,17141,121,17302,119,17461,121,17622,119,17783,117,17944,115,18104,115,18265,113,18426,111,18586,111,18747,109,18908,107,19069,105,19230,103,19389,105,19550,103,19711,101,19872,99,20033,97,20194,95,20355,93,20516,91,20677,89,20838,87,20999,85,21160,1,21162,79,21242,1,21323,77,21484,75,21645,73,21807,69,21968,67,22130,63,22291,1,22293,57,22351,1,22454,55,22616,1,22618,47,22666,1,22779,45,22942,40,23105,33,23270,23,23434,2,23437,2,23440,3,23444,2,23447,2]" Type="5" Size="4" Color="7" Angle="6" /></Layout></Component></Struct></Panel><Panel><Struct name="Singleton"><Component id="0" name="Grid"><Layout name="Center_Single" Number="0" Position="[[0.5, 0.5, 1, 1]]" Uniformity="3"><Entity bbox="[0.5, 0.5, 1, 1]" real_bbox="[0.5, 0.5, 0.5933, 0.5933]" mask="[5189,1,5348,6,5507,9,5517,2,5666,16,5825,19,5845,2,5984,25,6143,30,6174,1,6302,35,6461,40,6620,43,6664,2,6779,50,6938,54,6993,1,7097,59,7256,61,7415,63,7574,64,7733,66,7892,66,8051,68,8210,69,8369,70,8528,72,8687,73,8846,74,9005,76,9164,77,9323,77,9482,79,9641,80,9800,82,9959,83,10118,84,10277,85,10436,87,10595,88,10754,90,10913,90,11074,90,11234,90,11394,90,11554,90,11715,90,11875,90,12036,90,12195,91,12355,90,12516,90,12676,90,12836,91,12997,90,13157,90,13318,90,13477,91,13637,90,13798,90,13958,90,14119,90,14279,90,14439,90,14599,90,14760,90,14919,90,15080,88,15240,87,15401,85,15561,84,15721,83,15881,82,16042,80,16202,79,16363,77,16522,77,16682,76,16843,74,17003,73,17163,72,17324,70,17484,69,17644,68,17805,66,17964,66,18125,64,18285,63,18446,61,18607,59,18769,1,18771,54,18934,50,19097,2,19100,43,19262,40,19426,35,19588,1,19590,30,19754,25,19916,2,19919,19,20081,16,20244,2,20247,9,20409,6,20573,1]" Type="4" Size="2" Color="4" Angle="6" /></Layout></Component></Struct></Panel><Panel><Struct name="Singleton"><Component id="0" name="Grid"><Layout name="Center_Single" Number="0" Position="[[0.5, 0.5, 1, 1]]" Uniformity="3"><Entity bbox="[0.5, 0.5, 1, 1]" real_bbox="[0.4912, 0.5088, 0.3811, 0.3811]" mask="[7765,1,7767,1,7923,6,8080,1,8082,8,8239,12,8397,15,8555,18,8712,22,8870,25,9029,27,9186,31,9344,34,9503,36,9661,39,9818,43,9976,46,10133,50,10292,52,10451,54,10612,54,10772,55,10933,55,11092,57,11252,58,11412,59,11572,60,11733,60,11893,61,12053,60,12213,61,12373,60,12534,59,12694,58,12853,58,13014,58,13174,57,13333,57,13494,56,13654,55,13814,55,13975,53,14134,54,14295,53,14455,52,14615,52,14775,51,14935,50,15096,49,15256,49,15416,48,15576,48,15736,47,15897,45,16056,46,16216,45,16377,44,16536,45,16697,43,16858,1,16860,2,16863,37,17028,31,17193,1,17195,24,17358,1,17361,1,17364,15,17529,4,17534,4,17696,1]" Type="3" Size="0" Color="3" Angle="6" /></Layout></Component></Struct></Panel><Panel><Struct name="Singleton"><Component id="0" name="Grid"><Layout name="Center_Single" Number="0" Position="[[0.5, 0.5, 1, 1]]" Uniformity="3"><Entity bbox="[0.5, 0.5, 1, 1]" real_bbox="[0.5, 0.5, 0.8188, 0.8188]" mask="[2314,2,2317,2,2320,3,2324,2,2327,1,2470,24,2625,33,2659,1,2782,40,2939,45,3096,1,3098,47,3146,1,3254,55,3310,1,3411,1,3413,59,3570,63,3728,67,3887,69,4045,73,4204,75,4363,77,4520,1,4522,79,4602,1,4679,85,4838,87,4997,89,5156,91,5315,93,5474,95,5633,97,5792,99,5951,101,6110,103,6269,105,6430,103,6589,105,6748,107,6907,109,7066,111,7226,111,7385,113,7544,115,7704,115,7863,117,8022,119,8181,119,8342,119,8501,121,8661,121,8820,123,8981,121,9140,123,9299,125,9459,125,9618,127,9778,127,9937,128,10098,127,10257,129,10417,129,10577,129,10737,129,10896,130,11057,130,11217,130,11376,131,11536,131,11696,132,11855,133,12016,131,12175,133,12335,133,12496,131,12655,133,12815,133,12975,133,13136,131,13295,133,13455,133,13616,131,13775,133,13935,133,14096,131,14256,131,14416,131,14576,131,14736,130,14897,129,15057,129,15217,129,15377,129,15538,127,15697,128,15858,127,16018,126,16179,125,16339,125,16500,123,16661,121,16820,123,16981,121,17141,121,17302,119,17461,119,17622,119,17783,117,17944,115,18104,115,18265,113,18426,111,18586,111,18747,109,18908,107,19069,105,19230,103,19389,105,19550,103,19711,101,19872,99,20033,97,20194,95,20355,93,20516,91,20677,89,20838,87,20999,85,21160,1,21162,79,21242,1,21323,77,21484,75,21645,73,21807,69,21968,67,22130,63,22291,1,22293,59,22454,55,22510,1,22616,1,22618,47,22666,1,22779,45,22941,41,23105,33,23139,1,23270,21,23293,1,23434,2,23437,2,23440,3,23444,2,23447,1]" Type="5" Size="4" Color="4" Angle="0" /></Layout></Component></Struct></Panel><Panel><Struct name="Singleton"><Component id="0" name="Grid"><Layout name="Center_Single" Number="0" Position="[[0.5, 0.5, 1, 1]]" Uniformity="3"><Entity bbox="[0.5, 0.5, 1, 1]" real_bbox="[0.5, 0.5, 0.5933, 0.5933]" mask="[5213,1,5369,6,5524,2,5527,9,5681,16,5836,2,5839,19,5994,25,6148,1,6150,30,6306,35,6462,40,6617,2,6620,43,6774,50,6929,1,6931,54,7087,59,7246,61,7405,63,7565,64,7724,66,7885,66,8044,68,8204,69,8364,70,8523,72,8683,73,8843,74,9002,76,9162,77,9323,77,9482,79,9642,80,9801,82,9961,83,10121,84,10281,85,10440,87,10600,88,10759,90,10920,90,11079,90,11239,90,11399,90,11559,90,11718,90,11878,90,12037,90,12197,91,12358,90,12517,90,12677,90,12836,91,12996,90,13156,90,13315,90,13475,91,13636,90,13795,90,13955,90,14114,90,14274,90,14434,90,14594,90,14753,90,14914,90,15075,88,15236,87,15397,85,15558,84,15719,83,15880,82,16041,80,16202,79,16363,77,16524,77,16685,76,16846,74,17007,73,17168,72,17329,70,17490,69,17651,68,17812,66,17973,66,18134,64,18295,63,18456,61,18617,59,18778,54,18833,1,18939,50,19100,43,19144,2,19261,40,19422,35,19583,30,19614,1,19744,25,19905,19,19925,2,20066,16,20227,9,20237,2,20388,6,20549,1]" Type="4" Size="2" Color="1" Angle="0" /></Layout></Component></Struct></Panel><Panel><Struct name="Singleton"><Component id="0" name="Grid"><Layout name="Center_Single" Number="0" Position="[[0.5, 0.5, 1, 1]]" Uniformity="3"><Entity bbox="[0.5, 0.5, 1, 1]" real_bbox="[0.489, 0.489, 0.4828, 0.4828]" mask="[6473,4,6632,7,6791,11,6950,14,7109,16,7268,19,7427,21,7449,1,7586,25,7745,28,7904,32,8063,35,8222,37,8381,41,8540,44,8699,47,8858,49,8908,1,9017,53,9176,56,9335,60,9494,62,9653,65,9812,67,9971,68,10130,70,10289,70,10448,71,10607,71,10766,73,10925,73,11084,74,11243,75,11402,76,11561,77,11721,76,11881,76,12041,76,12202,75,12362,75,12523,73,12683,73,12843,74,13004,72,13164,72,13325,71,13486,70,13646,70,13807,69,13968,67,14127,68,14288,67,14449,66,14609,65,14770,65,14930,64,15090,64,15251,64,15411,63,15572,62,15733,61,15893,60,16053,61,16214,59,16374,59,16535,58,16695,58,16856,57,17017,55,17176,56,17337,55,17498,54,17658,53,17819,48,17979,41,18021,1,18139,33,18173,1,18176,1,18300,28,18461,18,18481,1,18621,13,18782,5,18788,1,18944,1]" Type="3" Size="1" Color="3" Angle="0" /></Layout></Component></Struct></Panel><Panel><Struct name="Singleton"><Component id="0" name="Grid"><Layout name="Center_Single" Number="0" Position="[[0.5, 0.5, 1, 1]]" Uniformity="3"><Entity bbox="[0.5, 0.5, 1, 1]" real_bbox="[0.4757, 0.4757, 0.3502, 0.3502]" mask="[7768,2,7927,4,8086,5,8245,7,8404,8,8563,10,8722,10,8881,11,9040,13,9199,14,9358,15,9517,17,9676,18,9835,20,9994,21,10153,23,10312,23,10471,24,10630,26,10789,27,10948,28,11107,30,11266,31,11425,33,11584,34,11743,34,11902,36,12061,37,12220,39,12379,40,12538,41,12697,42,12856,44,13015,45,13174,46,13333,47,13492,49,13651,50,13810,52,13969,52,14129,53,14290,52,14452,51,14614,1,14617,45,14780,43,14942,41,15104,1,15107,37,15270,34,15432,2,15435,30,15597,27,15761,24,15925,20,16087,1,16089,16,16251,1,16253,12,16415,11,16577,1,16579,7,16743,3]" Type="1" Size="0" Color="3" Angle="0" /></Layout></Component></Struct></Panel><Panel><Struct name="Singleton"><Component id="0" name="Grid"><Layout name="Center_Single" Number="0" Position="[[0.5, 0.5, 1, 1]]" Uniformity="3"><Entity bbox="[0.5, 0.5, 1, 1]" real_bbox="[0.4912, 0.4912, 0.3811, 0.3811]" mask="[7755,1,7757,1,7914,6,8073,8,8082,1,8232,12,8391,15,8550,18,8709,22,8868,25,9027,27,9186,31,9345,34,9504,36,9663,39,9822,43,9981,46,10140,50,10299,52,10458,54,10617,54,10776,55,10935,55,11094,57,11253,58,11412,59,11571,60,11730,60,11889,61,12050,60,12209,61,12370,60,12530,59,12691,58,12852,58,13011,58,13172,57,13333,57,13493,56,13654,55,13814,55,13975,53,14135,54,14295,53,14456,52,14616,52,14777,51,14938,50,15098,49,15258,49,15419,48,15579,48,15740,47,15901,45,16061,46,16222,45,16382,44,16542,45,16703,43,16863,37,16901,2,16904,1,17024,31,17184,24,17209,1,17344,15,17361,1,17364,1,17505,4,17510,4,17666,1]" Type="3" Size="0" Color="3" Angle="0" /></Layout></Component></Struct></Panel><Panel><Struct name="Singleton"><Component id="0" name="Grid"><Layout name="Center_Single" Number="0" Position="[[0.5, 0.5, 1, 1]]" Uniformity="3"><Entity bbox="[0.5, 0.5, 1, 1]" real_bbox="[0.4779, 0.4779, 0.8584, 0.8584]" mask="[1349,3,1508,6,1667,10,1826,13,1985,15,2144,18,2303,20,2324,1,2462,24,2621,26,2780,29,2939,33,3098,36,3257,38,3416,41,3575,43,3619,1,3734,47,3893,50,4052,54,4211,57,4370,59,4529,63,4688,66,4847,68,5006,71,5165,75,5324,78,5483,80,5642,82,5725,1,5801,86,5960,89,6119,91,6278,94,6437,98,6596,101,6755,103,6859,1,6914,107,7073,110,7232,112,7391,115,7550,117,7709,118,7868,120,8027,120,8186,121,8345,122,8504,123,8663,123,8822,124,8981,125,9140,126,9299,127,9458,127,9617,128,9776,130,9935,131,10094,131,10253,132,10412,133,10571,134,10730,135,10889,135,11049,135,11209,135,11370,134,11530,134,11691,133,11851,132,12011,132,12172,131,12332,130,12493,130,12654,129,12814,128,12975,128,13136,126,13295,127,13456,126,13617,125,13778,124,13938,123,14099,122,14259,122,14419,122,14580,121,14740,120,14901,120,15062,119,15222,118,15383,117,15544,115,15703,117,15864,116,16025,114,16185,114,16346,113,16506,113,16666,113,16827,112,16987,112,17148,110,17309,109,17469,110,17629,109,17790,108,17950,108,18111,107,18272,106,18432,105,18593,104,18753,104,18913,104,19074,102,19234,102,19395,102,19556,100,19717,99,19876,99,20037,98,20198,98,20358,98,20519,96,20680,95,20840,95,21001,94,21161,93,21321,92,21482,83,21567,2,21642,78,21722,1,21803,73,21964,64,22030,1,22123,55,22179,2,22284,49,22334,2,22445,43,22605,33,22639,2,22642,1,22766,29,22927,22,23087,13,23102,2,23248,7,23410,1]" Type="3" Size="5" Color="3" Angle="0" /></Layout></Component></Struct></Panel><Panel><Struct name="Singleton"><Component id="0" name="Grid"><Layout name="Center_Single" Number="0" Position="[[0.5, 0.5, 1, 1]]" Uniformity="3"><Entity bbox="[0.5, 0.5, 1, 1]" real_bbox="[0.5, 0.5, 0.3988, 0.3988]" mask="[7765,1,7767,3,7921,1,7923,8,8079,13,8234,19,8391,23,8546,1,8548,27,8702,1,8704,32,8858,1,8860,37,9017,41,9176,43,9337,43,9496,45,9656,46,9815,48,9976,48,10135,50,10295,51,10454,53,10615,53,10774,55,10934,56,11094,57,11253,59,11413,60,11573,61,11732,62,11892,62,12052,61,12212,62,12372,61,12531,62,12691,61,12850,63,13011,61,13170,62,13330,61,13489,62,13650,61,13809,62,13969,62,14129,61,14290,60,14451,59,14612,57,14773,56,14934,55,15095,53,15256,53,15417,51,15578,50,15739,48,15900,48,16061,46,16222,45,16383,43,16544,43,16705,41,16866,37,16904,1,17027,32,17060,1,17188,27,17216,1,17349,23,17510,19,17671,13,17832,8,17841,1,17993,3,17997,1]" Type="4" Size="0" Color="3" Angle="0" /></Layout></Component></Struct></Panel><Panel><Struct name="Singleton"><Component id="0" name="Grid"><Layout name="Center_Single" Number="0" Position="[[0.5, 0.5, 1, 1]]" Uniformity="3"><Entity bbox="[0.5, 0.5, 1, 1]" real_bbox="[0.4801, 0.4801, 0.7568, 0.7568]" mask="[2632,1,2790,5,2949,7,3108,10,3267,14,3426,16,3585,19,3744,23,3903,26,4062,28,4091,1,4221,32,4380,35,4539,37,4698,40,4857,42,4900,1,5016,46,5175,49,5334,51,5386,1,5493,55,5652,58,5811,61,5970,63,6129,67,6288,70,6447,72,6520,1,6606,76,6765,79,6924,81,7006,1,7083,85,7242,88,7401,91,7560,93,7654,1,7719,97,7878,100,8037,102,8196,104,8355,105,8514,106,8673,106,8832,107,8991,108,9150,109,9309,110,9468,110,9627,111,9786,113,9945,113,10104,114,10263,115,10422,115,10581,117,10740,118,10899,118,11058,119,11218,119,11377,120,11538,119,11698,119,11859,117,12020,116,12180,116,12341,115,12501,115,12661,115,12822,113,12983,113,13143,113,13304,111,13464,111,13624,111,13785,110,13945,110,14106,108,14267,107,14426,108,14587,107,14748,106,14908,106,15069,105,15230,103,15390,103,15551,103,15712,101,15871,102,16032,101,16193,100,16353,100,16514,98,16675,97,16834,98,16995,97,17156,96,17316,95,17477,95,17637,94,17798,93,17959,93,18119,92,18279,92,18440,91,18600,90,18761,90,18922,88,19081,89,19242,88,19403,87,19563,87,19724,85,19885,84,20044,85,20205,84,20366,82,20526,78,20687,70,20758,1,20847,62,20910,1,20913,1,21008,56,21169,47,21218,1,21328,41,21489,32,21522,2,21650,25,21810,16,21827,2,21971,9,21982,1,22132,3]" Type="3" Size="4" Color="3" Angle="0" /></Layout></Component></Struct></Panel><Panel><Struct name="Singleton"><Component id="0" name="Grid"><Layout name="Center_Single" Number="0" Position="[[0.5, 0.5, 1, 1]]" Uniformity="3"><Entity bbox="[0.5, 0.5, 1, 1]" real_bbox="[0.4912, 0.4912, 0.3811, 0.3811]" mask="[7755,1,7757,1,7914,6,8073,8,8082,1,8232,12,8391,15,8550,18,8709,22,8868,25,9027,27,9186,31,9345,34,9504,36,9663,39,9822,43,9981,46,10140,50,10299,52,10458,54,10617,54,10776,55,10935,55,11094,57,11253,58,11412,59,11571,60,11730,60,11889,61,12050,60,12209,61,12370,60,12530,59,12691,58,12852,58,13011,58,13172,57,13333,57,13493,56,13654,55,13814,55,13975,53,14135,54,14295,53,14456,52,14616,52,14777,51,14938,50,15098,49,15258,49,15419,48,15579,48,15740,47,15901,45,16061,46,16222,45,16382,44,16542,45,16703,43,16863,37,16901,2,16904,1,17024,31,17184,24,17209,1,17344,15,17361,1,17364,1,17505,4,17510,4,17666,1]" Type="3" Size="0" Color="7" Angle="0" /></Layout></Component></Struct></Panel><Panel><Struct name="Singleton"><Component id="0" name="Grid"><Layout name="Center_Single" Number="0" Position="[[0.5, 0.5, 1, 1]]" Uniformity="3"><Entity bbox="[0.5, 0.5, 1, 1]" real_bbox="[0.4912, 0.4912, 0.3811, 0.3811]" mask="[7755,1,7757,1,7914,6,8073,8,8082,1,8232,12,8391,15,8550,18,8709,22,8868,25,9027,27,9186,31,9345,34,9504,36,9663,39,9822,43,9981,46,10140,50,10299,52,10458,54,10617,54,10776,55,10935,55,11094,57,11253,58,11412,59,11571,60,11730,60,11889,61,12050,60,12209,61,12370,60,12530,59,12691,58,12852,58,13011,58,13172,57,13333,57,13493,56,13654,55,13814,55,13975,53,14135,54,14295,53,14456,52,14616,52,14777,51,14938,50,15098,49,15258,49,15419,48,15579,48,15740,47,15901,45,16061,46,16222,45,16382,44,16542,45,16703,43,16863,37,16901,2,16904,1,17024,31,17184,24,17209,1,17344,15,17361,1,17364,1,17505,4,17510,4,17666,1]" Type="3" Size="0" Color="4" Angle="0" /></Layout></Component></Struct></Panel></Panels><Rules><Rule_Group id="0"><Rule name="Constant" attr="Number/Position" /><Rule name="Progression" attr="Type" /><Rule name="Progression" attr="Size" /><Rule name="Arithmetic" attr="Color" /></Rule_Group></Rules></Data>