<Data><Panels><Panel><Struct name="Up_Down"><Component id="0" name="Up"><Layout name="Up_Center_Single" Number="0" Position="[[0.25, 0.5, 0.5, 0.5]]" Uniformity="0"><Entity bbox="[0.25, 0.5, 0.5, 0.5]" real_bbox="[0.2719, 0.5, 0.425, 0.4438]" mask="[1660,43,1819,45,1979,45,2138,47,2298,47,2458,47,2617,49,2777,49,2937,49,3096,51,3256,51,3416,51,3575,53,3735,53,3895,53,4054,55,4214,55,4374,55,4534,55,4693,57,4853,57,5013,57,5172,59,5332,59,5492,59,5651,61,5811,61,5971,61,6130,63,6290,63,6450,63,6609,65,6769,65,6929,65,7088,67,7248,67,7408,67,7567,69,7727,69,7887,69,8046,71,8206,71,8366,71,8527,69,8689,65,8850,63,9012,59,9173,57,9334,55,9496,51,9657,49,9818,47,9980,43,10141,41,10302,39,10464,35,10625,33,10786,31,10948,27,11109,25,11271,21,11432,19,11593,17,11755,13,11916,11,12077,9,12239,5,12400,3]" Type="3" Size="5" Color="0" Angle="7" /></Layout></Component><Component id="1" name="Down"><Layout name="Down_Center_Single" Number="0" Position="[[0.75, 0.5, 0.5, 0.5]]" Uniformity="3"><Entity bbox="[0.75, 0.5, 0.5, 0.5]" real_bbox="[0.75, 0.5156, 0.2937, 0.2875]" mask="[15607,3,15764,7,15921,10,16077,15,16234,19,16391,23,16548,26,16704,31,16862,34,17021,36,17181,37,17341,37,17501,38,17661,39,17821,40,17981,40,18141,41,18301,42,18461,43,18621,43,18781,44,18941,45,19101,46,19261,46,19421,46,19581,45,19741,44,19901,43,20061,43,20221,42,20381,41,20541,40,20701,40,20861,39,21021,38,21181,37,21341,37,21501,36,21662,34,21824,31,21988,26,22151,23,22314,19,22477,15,22641,10,22804,7,22967,3]" Type="3" Size="2" Color="8" Angle="1" /></Layout></Component></Struct></Panel><Panel><Struct name="Up_Down"><Component id="0" name="Up"><Layout name="Up_Center_Single" Number="0" Position="[[0.25, 0.5, 0.5, 0.5]]" Uniformity="0"><Entity bbox="[0.25, 0.5, 0.5, 0.5]" real_bbox="[0.2938, 0.5, 0.2812, 0.3188]" mask="[4057,49,4216,51,4377,49,4537,49,4698,47,4858,47,5019,45,5180,43,5340,43,5501,41,5661,41,5822,39,5982,39,6143,37,6304,35,6464,35,6625,33,6785,33,6946,31,7106,31,7267,29,7428,27,7588,27,7749,25,7909,25,8070,23,8230,23,8391,21,8552,19,8712,19,8873,17,9033,17,9194,15,9354,15,9515,13,9676,11,9836,11,9997,9,10157,9,10318,7,10478,7,10639,5,10800,3,10960,3,11121,1]" Type="1" Size="3" Color="0" Angle="7" /></Layout></Component><Component id="1" name="Down"><Layout name="Down_Center_Single" Number="0" Position="[[0.75, 0.5, 0.5, 0.5]]" Uniformity="3"><Entity bbox="[0.75, 0.5, 0.5, 0.5]" real_bbox="[0.75, 0.5, 0.1938, 0.1938]" mask="[16867,29,17026,31,17186,31,17346,31,17506,31,17666,31,17826,31,17986,31,18146,31,18306,31,18466,31,18626,31,18786,31,18946,31,19106,31,19266,31,19426,31,19586,31,19746,31,19906,31,20066,31,20226,31,20386,31,20546,31,20706,31,20866,31,21026,31,21186,31,21346,31,21506,31,21667,29]" Type="2" Size="1" Color="6" Angle="1" /></Layout></Component></Struct></Panel><Panel><Struct name="Up_Down"><Component id="0" name="Up"><Layout name="Up_Center_Single" Number="0" Position="[[0.25, 0.5, 0.5, 0.5]]" Uniformity="0"><Entity bbox="[0.25, 0.5, 0.5, 0.5]" real_bbox="[0.25, 0.5, 0.2688, 0.2688]" mask="[3117,9,3274,15,3432,19,3589,24,3749,25,3907,29,4066,31,4225,33,4385,33,4543,37,4703,37,4863,37,5022,39,5182,39,5341,41,5501,41,5661,41,5820,43,5980,43,6140,43,6300,43,6460,43,6620,43,6780,43,6940,43,7100,43,7261,41,7421,41,7581,41,7742,39,7902,39,8063,37,8223,37,8384,35,8545,33,8705,33,8866,31,9027,29,9189,25,9349,24,9512,19,9674,15,9837,9]" Type="5" Size="1" Color="0" Angle="7" /></Layout></Component><Component id="1" name="Down"><Layout name="Down_Center_Single" Number="0" Position="[[0.75, 0.5, 0.5, 0.5]]" Uniformity="3"><Entity bbox="[0.75, 0.5, 0.5, 0.5]" real_bbox="[0.75, 0.5, 0.4188, 0.4188]" mask="[13995,13,14151,20,14309,25,14467,29,14624,35,14783,37,14942,39,15100,43,15259,45,15418,47,15577,49,15736,51,15895,53,16055,53,16214,55,16373,57,16532,59,16692,59,16852,59,17011,61,17171,61,17330,63,17490,63,17650,63,17809,65,17969,65,18129,65,18288,67,18448,67,18608,67,18768,67,18928,67,19088,67,19248,67,19408,67,19568,67,19728,67,19888,67,20048,67,20208,67,20369,65,20529,65,20689,65,20849,65,21010,63,21170,63,21331,61,21491,61,21652,59,21812,59,21972,59,22133,57,22294,55,22455,53,22615,53,22776,51,22937,49,23098,47,23259,45,23420,43,23582,39,23743,37,23904,35,24067,29,24229,25,24391,20,24555,13]" Type="5" Size="4" Color="4" Angle="1" /></Layout></Component></Struct></Panel><Panel><Struct name="Up_Down"><Component id="0" name="Up"><Layout name="Up_Center_Single" Number="0" Position="[[0.25, 0.5, 0.5, 0.5]]" Uniformity="0"><Entity bbox="[0.25, 0.5, 0.5, 0.5]" real_bbox="[0.25, 0.5, 0.4688, 0.4688]" mask="[394,1,401,1,552,16,569,2,708,27,867,29,1025,33,1182,39,1341,41,1500,43,1658,47,1817,49,1976,51,2135,53,2294,55,2453,57,2612,59,2771,61,2931,61,3090,63,3249,65,3408,67,3568,67,3728,67,3887,69,4047,69,4206,71,4365,73,4525,73,4685,73,4845,73,5004,75,5164,75,5325,75,5484,75,5644,75,5804,75,5964,75,6124,75,6284,75,6443,77,6604,75,6764,75,6924,75,7084,75,7244,75,7404,75,7565,75,7724,75,7884,75,8045,73,8205,73,8365,73,8525,73,8686,71,8847,69,9007,69,9168,67,9328,67,9488,67,9649,65,9810,63,9971,61,10131,61,10292,59,10453,57,10614,55,10775,53,10936,51,11097,49,11258,47,11420,43,11581,41,11742,39,11905,33,12067,29,12228,27,12392,16,12409,2,12554,1,12561,1]" Type="5" Size="5" Color="8" Angle="4" /></Layout></Component><Component id="1" name="Down"><Layout name="Down_Center_Single" Number="0" Position="[[0.75, 0.5, 0.5, 0.5]]" Uniformity="3"><Entity bbox="[0.75, 0.5, 0.5, 0.5]" real_bbox="[0.75, 0.5, 0.3188, 0.3188]" mask="[15116,1,15119,1,15121,1,15123,1,15126,1,15274,15,15430,23,15589,25,15748,27,15906,31,16065,33,16224,35,16383,37,16542,39,16701,41,16860,43,17020,43,17179,45,17338,47,17497,49,17657,49,17817,49,17977,49,18136,51,18296,51,18455,53,18616,51,18776,51,18935,53,19095,53,19255,53,19416,51,19575,53,19736,51,19896,51,20055,53,20216,51,20376,51,20537,49,20697,49,20857,49,21017,49,21178,47,21339,45,21500,43,21660,43,21821,41,21982,39,22143,37,22304,35,22465,33,22626,31,22788,27,22949,25,23110,23,23274,15,23436,1,23439,5,23446,1]" Type="5" Size="2" Color="5" Angle="6" /></Layout></Component></Struct></Panel><Panel><Struct name="Up_Down"><Component id="0" name="Up"><Layout name="Up_Center_Single" Number="0" Position="[[0.25, 0.5, 0.5, 0.5]]" Uniformity="0"><Entity bbox="[0.25, 0.5, 0.5, 0.5]" real_bbox="[0.2588, 0.5088, 0.3369, 0.3369]" mask="[2332,3,2482,1,2484,2,2487,9,2636,21,2786,1,2789,1,2791,26,2941,1,2943,35,3100,38,3259,39,3420,39,3579,40,3739,41,3899,42,4058,43,4219,42,4379,43,4538,44,4699,44,4858,46,5018,46,5178,47,5338,47,5498,47,5657,49,5817,50,5977,50,6137,51,6297,51,6457,51,6616,53,6777,52,6936,54,7096,54,7257,53,7416,53,7576,52,7736,51,7896,50,8056,49,8215,49,8375,48,8535,47,8696,45,8857,43,9019,40,9182,36,9344,33,9505,31,9668,27,9830,24,9991,22,10153,19,10316,15,10477,13,10639,10,10802,6,10964,3]" Type="3" Size="3" Color="6" Angle="4" /></Layout></Component><Component id="1" name="Down"><Layout name="Down_Center_Single" Number="0" Position="[[0.75, 0.5, 0.5, 0.5]]" Uniformity="3"><Entity bbox="[0.75, 0.5, 0.5, 0.5]" real_bbox="[0.7456, 0.5044, 0.1955, 0.1955]" mask="[16722,3,16880,6,17037,10,17195,13,17352,17,17511,19,17667,24,17826,26,17985,28,18146,28,18306,29,18467,29,18626,31,18786,32,18947,31,19106,32,19266,31,19427,30,19587,29,19747,29,19907,29,20067,28,20227,28,20387,27,20548,26,20708,26,20867,26,21028,24,21188,24,21349,23,21511,1,21514,18,21681,2,21684,2,21687,4,21849,1]" Type="3" Size="0" Color="3" Angle="6" /></Layout></Component></Struct></Panel><Panel><Struct name="Up_Down"><Component id="0" name="Up"><Layout name="Up_Center_Single" Number="0" Position="[[0.25, 0.5, 0.5, 0.5]]" Uniformity="0"><Entity bbox="[0.25, 0.5, 0.5, 0.5]" real_bbox="[0.2655, 0.5155, 0.2265, 0.2265]" mask="[3906,1,4065,4,4070,2,4226,9,4386,11,4399,1,4547,15,4706,20,4866,22,4889,1,5027,25,5053,1,5187,29,5217,1,5347,33,5508,34,5668,34,5829,33,5989,32,6148,32,6309,30,6469,29,6630,27,6790,26,6950,25,7110,24,7271,22,7431,21,7592,19,7751,19,7912,17,8072,16,8233,14,8392,14,8553,12,8713,11,8874,9,9033,9,9194,7,9354,6,9515,4,9675,3]" Type="1" Size="1" Color="2" Angle="4" /></Layout></Component><Component id="1" name="Down"><Layout name="Down_Center_Single" Number="0" Position="[[0.75, 0.5, 0.5, 0.5]]" Uniformity="3"><Entity bbox="[0.75, 0.5, 0.5, 0.5]" real_bbox="[0.75, 0.5, 0.3546, 0.3546]" mask="[14800,3,14959,5,15118,7,15277,9,15436,11,15595,13,15754,15,15913,17,16072,19,16231,21,16390,23,16549,25,16708,27,16867,29,17026,31,17185,33,17344,35,17503,37,17662,39,17821,41,17980,43,18139,45,18298,47,18457,49,18616,51,18775,53,18934,55,19093,57,19253,57,19413,57,19574,55,19735,53,19896,51,20057,49,20218,47,20379,45,20540,43,20701,41,20862,39,21023,37,21184,35,21345,33,21506,31,21667,29,21828,27,21989,25,22150,23,22311,21,22472,19,22633,17,22794,15,22955,13,23116,11,23277,9,23438,7,23599,5,23760,3]" Type="2" Size="3" Color="1" Angle="6" /></Layout></Component></Struct></Panel><Panel><Struct name="Up_Down"><Component id="0" name="Up"><Layout name="Up_Center_Single" Number="0" Position="[[0.25, 0.5, 0.5, 0.5]]" Uniformity="0"><Entity bbox="[0.25, 0.5, 0.5, 0.5]" real_bbox="[0.2257, 0.4757, 0.3502, 0.3502]" mask="[1368,2,1527,4,1686,5,1845,7,2004,8,2163,10,2322,10,2481,11,2640,13,2799,14,2958,15,3117,17,3276,18,3435,20,3594,21,3753,23,3912,23,4071,24,4230,26,4389,27,4548,28,4707,30,4866,31,5025,33,5184,34,5343,34,5502,36,5661,37,5820,39,5979,40,6138,41,6297,42,6456,44,6615,45,6774,46,6933,47,7092,49,7251,50,7410,52,7569,52,7729,53,7890,52,8052,51,8214,1,8217,45,8380,43,8542,41,8704,1,8707,37,8870,34,9032,2,9035,30,9197,27,9361,24,9525,20,9687,1,9689,16,9851,1,9853,12,10015,11,10177,1,10179,7,10343,3]" Type="1" Size="4" Color="7" Angle="0" /></Layout></Component><Component id="1" name="Down"><Layout name="Down_Center_Single" Number="0" Position="[[0.75, 0.5, 0.5, 0.5]]" Uniformity="3"><Entity bbox="[0.75, 0.5, 0.5, 0.5]" real_bbox="[0.75, 0.5, 0.2662, 0.2662]" mask="[15920,3,16079,5,16238,7,16397,9,16556,11,16715,13,16874,15,17033,17,17192,19,17351,21,17510,23,17669,25,17828,27,17987,29,18146,31,18305,33,18464,35,18623,37,18782,39,18941,41,19100,43,19260,43,19420,43,19581,41,19742,39,19903,37,20064,35,20225,33,20386,31,20547,29,20708,27,20869,25,21030,23,21191,21,21352,19,21513,17,21674,15,21835,13,21996,11,22157,9,22318,7,22479,5,22640,3]" Type="2" Size="1" Color="5" Angle="6" /></Layout></Component></Struct></Panel><Panel><Struct name="Up_Down"><Component id="0" name="Up"><Layout name="Up_Center_Single" Number="0" Position="[[0.25, 0.5, 0.5, 0.5]]" Uniformity="0"><Entity bbox="[0.25, 0.5, 0.5, 0.5]" real_bbox="[0.25, 0.5, 0.3188, 0.3188]" mask="[2316,1,2319,3,2323,1,2326,1,2474,15,2630,23,2789,25,2948,27,3106,31,3265,33,3424,35,3583,37,3742,39,3901,41,4060,43,4220,43,4379,45,4538,47,4697,49,4857,49,5017,49,5177,49,5336,51,5496,51,5655,53,5816,51,5976,51,6135,53,6296,52,6455,53,6616,52,6775,53,6936,51,7096,51,7255,53,7416,51,7576,51,7737,49,7897,49,8057,49,8217,49,8378,47,8539,45,8700,43,8860,43,9021,41,9182,39,9343,37,9504,35,9665,33,9826,31,9988,27,10149,25,10310,23,10474,15,10636,1,10639,3,10643,1,10646,1]" Type="5" Size="2" Color="4" Angle="0" /></Layout></Component><Component id="1" name="Down"><Layout name="Down_Center_Single" Number="0" Position="[[0.75, 0.5, 0.5, 0.5]]" Uniformity="3"><Entity bbox="[0.75, 0.5, 0.5, 0.5]" real_bbox="[0.75, 0.5, 0.2188, 0.2188]" mask="[16397,2,16401,1,16404,2,16554,15,16712,19,16871,21,17030,23,17189,25,17348,27,17507,29,17666,31,17826,31,17985,33,18144,35,18304,35,18464,35,18623,37,18783,37,18944,35,19104,35,19263,37,19424,35,19584,35,19743,37,19903,37,20064,35,20224,35,20384,35,20545,33,20705,33,20866,31,21027,29,21188,27,21349,25,21510,23,21671,21,21833,17,21994,15,22157,2,22161,1,22164,2]" Type="5" Size="0" Color="3" Angle="6" /></Layout></Component></Struct></Panel><Panel><Struct name="Up_Down"><Component id="0" name="Up"><Layout name="Up_Center_Single" Number="0" Position="[[0.25, 0.5, 0.5, 0.5]]" Uniformity="0"><Entity bbox="[0.25, 0.5, 0.5, 0.5]" real_bbox="[0.2456, 0.4956, 0.1955, 0.1955]" mask="[3918,3,4077,6,4236,10,4395,13,4554,17,4713,19,4872,24,5031,26,5190,28,5349,28,5508,29,5667,29,5826,31,5985,32,6145,31,6305,32,6466,31,6626,30,6787,29,6947,29,7107,29,7268,28,7428,28,7589,27,7749,26,7909,26,8070,26,8231,24,8391,24,8551,23,8711,18,8731,1,8872,4,8877,2,8880,2,9033,1]" Type="3" Size="0" Color="3" Angle="0" /></Layout></Component><Component id="1" name="Down"><Layout name="Down_Center_Single" Number="0" Position="[[0.75, 0.5, 0.5, 0.5]]" Uniformity="3"><Entity bbox="[0.75, 0.5, 0.5, 0.5]" real_bbox="[0.7412, 0.5088, 0.2928, 0.2928]" mask="[15284,2,15441,6,15600,8,15758,11,15917,13,16075,16,16232,20,16390,23,16549,25,16706,1,16708,27,16865,31,17023,34,17182,36,17340,39,17499,41,17659,42,17818,44,17979,44,18139,45,18299,46,18460,46,18619,48,18780,47,18940,46,19100,46,19260,46,19420,45,19580,44,19740,44,19901,42,20061,41,20221,41,20380,41,20541,40,20701,40,20862,38,21021,39,21181,38,21342,36,21502,35,21662,36,21822,35,21982,34,22143,33,22304,31,22469,2,22472,22,22634,1,22638,16,22805,1,22807,6,22970,1]" Type="3" Size="2" Color="5" Angle="6" /></Layout></Component></Struct></Panel><Panel><Struct name="Up_Down"><Component id="0" name="Up"><Layout name="Up_Center_Single" Number="0" Position="[[0.25, 0.5, 0.5, 0.5]]" Uniformity="0"><Entity bbox="[0.25, 0.5, 0.5, 0.5]" real_bbox="[0.2456, 0.4956, 0.1955, 0.1955]" mask="[3918,3,4077,6,4236,10,4395,13,4554,17,4713,19,4872,24,5031,26,5190,28,5349,28,5508,29,5667,29,5826,31,5985,32,6145,31,6305,32,6466,31,6626,30,6787,29,6947,29,7107,29,7268,28,7428,28,7589,27,7749,26,7909,26,8070,26,8231,24,8391,24,8551,23,8711,18,8731,1,8872,4,8877,2,8880,2,9033,1]" Type="3" Size="0" Color="1" Angle="0" /></Layout></Component><Component id="1" name="Down"><Layout name="Down_Center_Single" Number="0" Position="[[0.75, 0.5, 0.5, 0.5]]" Uniformity="3"><Entity bbox="[0.75, 0.5, 0.5, 0.5]" real_bbox="[0.7412, 0.5088, 0.2928, 0.2928]" mask="[15284,2,15441,6,15600,8,15758,11,15917,13,16075,16,16232,20,16390,23,16549,25,16706,1,16708,27,16865,31,17023,34,17182,36,17340,39,17499,41,17659,42,17818,44,17979,44,18139,45,18299,46,18460,46,18619,48,18780,47,18940,46,19100,46,19260,46,19420,45,19580,44,19740,44,19901,42,20061,41,20221,41,20380,41,20541,40,20701,40,20862,38,21021,39,21181,38,21342,36,21502,35,21662,36,21822,35,21982,34,22143,33,22304,31,22469,2,22472,22,22634,1,22638,16,22805,1,22807,6,22970,1]" Type="3" Size="2" Color="1" Angle="6" /></Layout></Component></Struct></Panel><Panel><Struct name="Up_Down"><Component id="0" name="Up"><Layout name="Up_Center_Single" Number="0" Position="[[0.25, 0.5, 0.5, 0.5]]" Uniformity="0"><Entity bbox="[0.25, 0.5, 0.5, 0.5]" real_bbox="[0.2456, 0.4956, 0.1955, 0.1955]" mask="[3918,3,4077,6,4236,10,4395,13,4554,17,4713,19,4872,24,5031,26,5190,28,5349,28,5508,29,5667,29,5826,31,5985,32,6145,31,6305,32,6466,31,6626,30,6787,29,6947,29,7107,29,7268,28,7428,28,7589,27,7749,26,7909,26,8070,26,8231,24,8391,24,8551,23,8711,18,8731,1,8872,4,8877,2,8880,2,9033,1]" Type="3" Size="0" Color="3" Angle="0" /></Layout></Component><Component id="1" name="Down"><Layout name="Down_Center_Single" Number="0" Position="[[0.75, 0.5, 0.5, 0.5]]" Uniformity="3"><Entity bbox="[0.75, 0.5, 0.5, 0.5]" real_bbox="[0.7412, 0.5088, 0.3811, 0.3811]" mask="[14165,1,14167,1,14323,6,14480,1,14482,8,14639,12,14797,15,14955,18,15112,22,15270,25,15429,27,15586,31,15744,34,15903,36,16061,39,16218,43,16376,46,16533,50,16692,52,16851,54,17012,54,17172,55,17333,55,17492,57,17652,58,17812,59,17972,60,18133,60,18293,61,18453,60,18613,61,18773,60,18934,59,19094,58,19253,58,19414,58,19574,57,19733,57,19894,56,20054,55,20214,55,20375,53,20534,54,20695,53,20855,52,21015,52,21175,51,21335,50,21496,49,21656,49,21816,48,21976,48,22136,47,22297,45,22456,46,22616,45,22777,44,22936,45,23097,43,23258,1,23260,2,23263,37,23428,31,23593,1,23595,24,23758,1,23761,1,23764,15,23929,4,23934,4,24096,1]" Type="3" Size="4" Color="1" Angle="6" /></Layout></Component></Struct></Panel><Panel><Struct name="Up_Down"><Component id="0" name="Up"><Layout name="Up_Center_Single" Number="0" Position="[[0.25, 0.5, 0.5, 0.5]]" Uniformity="0"><Entity bbox="[0.25, 0.5, 0.5, 0.5]" real_bbox="[0.2456, 0.4956, 0.1955, 0.1955]" mask="[3918,3,4077,6,4236,10,4395,13,4554,17,4713,19,4872,24,5031,26,5190,28,5349,28,5508,29,5667,29,5826,31,5985,32,6145,31,6305,32,6466,31,6626,30,6787,29,6947,29,7107,29,7268,28,7428,28,7589,27,7749,26,7909,26,8070,26,8231,24,8391,24,8551,23,8711,18,8731,1,8872,4,8877,2,8880,2,9033,1]" Type="3" Size="0" Color="3" Angle="0" /></Layout></Component><Component id="1" name="Down"><Layout name="Down_Center_Single" Number="0" Position="[[0.75, 0.5, 0.5, 0.5]]" Uniformity="3"><Entity bbox="[0.75, 0.5, 0.5, 0.5]" real_bbox="[0.7412, 0.5088, 0.2928, 0.2928]" mask="[15284,2,15441,6,15600,8,15758,11,15917,13,16075,16,16232,20,16390,23,16549,25,16706,1,16708,27,16865,31,17023,34,17182,36,17340,39,17499,41,17659,42,17818,44,17979,44,18139,45,18299,46,18460,46,18619,48,18780,47,18940,46,19100,46,19260,46,19420,45,19580,44,19740,44,19901,42,20061,41,20221,41,20380,41,20541,40,20701,40,20862,38,21021,39,21181,38,21342,36,21502,35,21662,36,21822,35,21982,34,22143,33,22304,31,22469,2,22472,22,22634,1,22638,16,22805,1,22807,6,22970,1]" Type="3" Size="2" Color="1" Angle="6" /></Layout></Component></Struct></Panel><Panel><Struct name="Up_Down"><Component id="0" name="Up"><Layout name="Up_Center_Single" Number="0" Position="[[0.25, 0.5, 0.5, 0.5]]" Uniformity="0"><Entity bbox="[0.25, 0.5, 0.5, 0.5]" real_bbox="[0.25, 0.5, 0.2188, 0.2188]" mask="[3597,2,3601,1,3604,2,3754,15,3913,18,4071,21,4230,23,4389,25,4548,27,4707,29,4866,31,5025,32,5185,33,5344,35,5504,35,5664,35,5823,37,5983,37,6144,35,6304,35,6463,37,6624,35,6784,35,6943,37,7103,37,7264,35,7424,35,7584,35,7745,33,7905,32,8066,31,8227,29,8388,27,8549,25,8710,23,8871,21,9033,18,9194,15,9357,2,9361,1,9364,2]" Type="5" Size="0" Color="3" Angle="0" /></Layout></Component><Component id="1" name="Down"><Layout name="Down_Center_Single" Number="0" Position="[[0.75, 0.5, 0.5, 0.5]]" Uniformity="3"><Entity bbox="[0.75, 0.5, 0.5, 0.5]" real_bbox="[0.7412, 0.5088, 0.2928, 0.2928]" mask="[15284,2,15441,6,15600,8,15758,11,15917,13,16075,16,16232,20,16390,23,16549,25,16706,1,16708,27,16865,31,17023,34,17182,36,17340,39,17499,41,17659,42,17818,44,17979,44,18139,45,18299,46,18460,46,18619,48,18780,47,18940,46,19100,46,19260,46,19420,45,19580,44,19740,44,19901,42,20061,41,20221,41,20380,41,20541,40,20701,40,20862,38,21021,39,21181,38,21342,36,21502,35,21662,36,21822,35,21982,34,22143,33,22304,31,22469,2,22472,22,22634,1,22638,16,22805,1,22807,6,22970,1]" Type="3" Size="2" Color="1" Angle="6" /></Layout></Component></Struct></Panel><Panel><Struct name="Up_Down"><Component id="0" name="Up"><Layout name="Up_Center_Single" Number="0" Position="[[0.25, 0.5, 0.5, 0.5]]" Uniformity="0"><Entity bbox="[0.25, 0.5, 0.5, 0.5]" real_bbox="[0.2456, 0.4956, 0.1955, 0.1955]" mask="[3918,3,4077,6,4236,10,4395,13,4554,17,4713,19,4872,24,5031,26,5190,28,5349,28,5508,29,5667,29,5826,31,5985,32,6145,31,6305,32,6466,31,6626,30,6787,29,6947,29,7107,29,7268,28,7428,28,7589,27,7749,26,7909,26,8070,26,8231,24,8391,24,8551,23,8711,18,8731,1,8872,4,8877,2,8880,2,9033,1]" Type="3" Size="0" Color="3" Angle="0" /></Layout></Component><Component id="1" name="Down"><Layout name="Down_Center_Single" Number="0" Position="[[0.75, 0.5, 0.5, 0.5]]" Uniformity="3"><Entity bbox="[0.75, 0.5, 0.5, 0.5]" real_bbox="[0.7456, 0.5044, 0.1955, 0.1955]" mask="[16722,3,16880,6,17037,10,17195,13,17352,17,17511,19,17667,24,17826,26,17985,28,18146,28,18306,29,18467,29,18626,31,18786,32,18947,31,19106,32,19266,31,19427,30,19587,29,19747,29,19907,29,20067,28,20227,28,20387,27,20548,26,20708,26,20867,26,21028,24,21188,24,21349,23,21511,1,21514,18,21681,2,21684,2,21687,4,21849,1]" Type="3" Size="0" Color="1" Angle="6" /></Layout></Component></Struct></Panel><Panel><Struct name="Up_Down"><Component id="0" name="Up"><Layout name="Up_Center_Single" Number="0" Position="[[0.25, 0.5, 0.5, 0.5]]" Uniformity="0"><Entity bbox="[0.25, 0.5, 0.5, 0.5]" real_bbox="[0.2456, 0.4956, 0.1955, 0.1955]" mask="[3918,3,4077,6,4236,10,4395,13,4554,17,4713,19,4872,24,5031,26,5190,28,5349,28,5508,29,5667,29,5826,31,5985,32,6145,31,6305,32,6466,31,6626,30,6787,29,6947,29,7107,29,7268,28,7428,28,7589,27,7749,26,7909,26,8070,26,8231,24,8391,24,8551,23,8711,18,8731,1,8872,4,8877,2,8880,2,9033,1]" Type="3" Size="0" Color="4" Angle="0" /></Layout></Component><Component id="1" name="Down"><Layout name="Down_Center_Single" Number="0" Position="[[0.75, 0.5, 0.5, 0.5]]" Uniformity="3"><Entity bbox="[0.75, 0.5, 0.5, 0.5]" real_bbox="[0.7412, 0.5088, 0.2928, 0.2928]" mask="[15284,2,15441,6,15600,8,15758,11,15917,13,16075,16,16232,20,16390,23,16549,25,16706,1,16708,27,16865,31,17023,34,17182,36,17340,39,17499,41,17659,42,17818,44,17979,44,18139,45,18299,46,18460,46,18619,48,18780,47,18940,46,19100,46,19260,46,19420,45,19580,44,19740,44,19901,42,20061,41,20221,41,20380,41,20541,40,20701,40,20862,38,21021,39,21181,38,21342,36,21502,35,21662,36,21822,35,21982,34,22143,33,22304,31,22469,2,22472,22,22634,1,22638,16,22805,1,22807,6,22970,1]" Type="3" Size="2" Color="1" Angle="6" /></Layout></Component></Struct></Panel><Panel><Struct name="Up_Down"><Component id="0" name="Up"><Layout name="Up_Center_Single" Number="0" Position="[[0.25, 0.5, 0.5, 0.5]]" Uniformity="0"><Entity bbox="[0.25, 0.5, 0.5, 0.5]" real_bbox="[0.2456, 0.4956, 0.1955, 0.1955]" mask="[3918,3,4077,6,4236,10,4395,13,4554,17,4713,19,4872,24,5031,26,5190,28,5349,28,5508,29,5667,29,5826,31,5985,32,6145,31,6305,32,6466,31,6626,30,6787,29,6947,29,7107,29,7268,28,7428,28,7589,27,7749,26,7909,26,8070,26,8231,24,8391,24,8551,23,8711,18,8731,1,8872,4,8877,2,8880,2,9033,1]" Type="3" Size="0" Color="3" Angle="0" /></Layout></Component><Component id="1" name="Down"><Layout name="Down_Center_Single" Number="0" Position="[[0.75, 0.5, 0.5, 0.5]]" Uniformity="3"><Entity bbox="[0.75, 0.5, 0.5, 0.5]" real_bbox="[0.7412, 0.5088, 0.3369, 0.3369]" mask="[14804,3,14962,6,15119,10,15277,13,15436,15,15593,19,15751,22,15910,24,16068,27,16225,31,16384,33,16542,36,16699,40,16857,43,17016,45,17175,47,17335,48,17495,49,17656,49,17816,50,17976,51,18136,52,18296,53,18457,53,18616,54,18776,54,18937,52,19096,53,19257,51,19417,51,19577,51,19737,50,19897,50,20057,49,20218,47,20378,47,20538,47,20698,46,20858,46,21019,44,21178,44,21339,43,21499,42,21658,43,21819,42,21979,41,22139,40,22300,39,22459,39,22620,38,22781,1,22783,35,22946,1,22949,1,22951,26,23116,21,23282,1,23284,2,23287,9,23452,3]" Type="3" Size="3" Color="1" Angle="6" /></Layout></Component></Struct></Panel></Panels><Rules><Rule_Group id="0"><Rule name="Constant" attr="Number/Position" /><Rule name="Distribute_Three" attr="Type" /><Rule name="Progression" attr="Size" /><Rule name="Arithmetic" attr="Color" /></Rule_Group><Rule_Group id="1"><Rule name="Constant" attr="Number/Position" /><Rule name="Distribute_Three" attr="Type" /><Rule name="Arithmetic" attr="Size" /><Rule name="Progression" attr="Color" /></Rule_Group></Rules></Data>