<Data><Panels><Panel><Struct name="Left_Right"><Component id="0" name="Left"><Layout name="Left_Center_Single" Number="0" Position="[[0.5, 0.25, 0.5, 0.5]]" Uniformity="2"><Entity bbox="[0.5, 0.25, 0.5, 0.5]" real_bbox="[0.5, 0.25, 0.2688, 0.2688]" mask="[9317,1,9319,5,9325,1,9474,1,9476,11,9488,1,9632,19,9789,1,9791,21,9813,1,9948,27,10107,29,10266,31,10425,33,10584,35,10743,37,10902,39,11063,37,11222,39,11381,41,11541,41,11700,43,11861,41,12020,43,12180,43,12340,43,12499,45,12659,45,12819,45,12979,45,13139,45,13300,43,13459,45,13620,43,13781,41,13940,43,14101,41,14261,41,14422,39,14583,37,14742,39,14903,37,15064,35,15225,33,15386,31,15547,29,15708,27,15869,1,15871,21,15893,1,16032,19,16194,1,16196,11,16208,1,16359,5]" Type="5" Size="1" Color="1" Angle="6" /></Layout></Component><Component id="1" name="Right"><Layout name="Right_Center_Single" Number="0" Position="[[0.5, 0.75, 0.5, 0.5]]" Uniformity="3"><Entity bbox="[0.5, 0.75, 0.5, 0.5]" real_bbox="[0.4956, 0.7544, 0.1955, 0.1955]" mask="[10362,3,10520,6,10677,10,10835,13,10992,17,11151,19,11307,24,11466,26,11625,28,11786,28,11946,29,12107,29,12266,31,12426,32,12587,31,12746,32,12906,31,13067,30,13227,29,13387,29,13547,29,13707,28,13867,28,14027,27,14188,26,14348,26,14507,26,14668,24,14828,24,14989,23,15151,1,15154,18,15321,2,15324,2,15327,4,15489,1]" Type="3" Size="0" Color="8" Angle="6" /></Layout></Component></Struct></Panel><Panel><Struct name="Left_Right"><Component id="0" name="Left"><Layout name="Left_Center_Single" Number="0" Position="[[0.5, 0.25, 0.5, 0.5]]" Uniformity="2"><Entity bbox="[0.5, 0.25, 0.5, 0.5]" real_bbox="[0.5, 0.25, 0.3188, 0.3188]" mask="[8676,1,8679,1,8681,1,8683,1,8686,1,8834,15,8990,23,9149,25,9308,27,9466,31,9625,33,9784,35,9943,37,10102,39,10261,41,10420,43,10580,43,10739,45,10898,47,11057,49,11217,49,11377,49,11537,49,11696,51,11856,51,12015,53,12176,51,12336,51,12495,53,12655,53,12815,53,12976,51,13135,53,13296,51,13456,51,13615,53,13776,51,13936,51,14097,49,14257,49,14417,49,14577,49,14738,47,14899,45,15060,43,15220,43,15381,41,15542,39,15703,37,15864,35,16025,33,16186,31,16348,27,16509,25,16670,23,16834,15,16996,1,16999,5,17006,1]" Type="5" Size="2" Color="1" Angle="6" /></Layout></Component><Component id="1" name="Right"><Layout name="Right_Center_Single" Number="0" Position="[[0.5, 0.75, 0.5, 0.5]]" Uniformity="3"><Entity bbox="[0.5, 0.75, 0.5, 0.5]" real_bbox="[0.4912, 0.7588, 0.3811, 0.3811]" mask="[7805,1,7807,1,7963,6,8120,1,8122,8,8279,12,8437,15,8595,18,8752,22,8910,25,9069,27,9226,31,9384,34,9543,36,9701,39,9858,43,10016,46,10173,50,10332,52,10491,54,10652,54,10812,55,10973,55,11132,57,11292,58,11452,59,11612,60,11773,60,11933,61,12093,60,12253,61,12413,60,12574,59,12734,58,12893,58,13054,58,13214,57,13373,57,13534,56,13694,55,13854,55,14015,53,14174,54,14335,53,14495,52,14655,52,14815,51,14975,50,15136,49,15296,49,15456,48,15616,48,15776,47,15937,45,16096,46,16256,45,16417,44,16576,45,16737,43,16898,1,16900,2,16903,37,17068,31,17233,1,17235,24,17398,1,17401,1,17404,15,17569,4,17574,4,17736,1]" Type="3" Size="4" Color="1" Angle="6" /></Layout></Component></Struct></Panel><Panel><Struct name="Left_Right"><Component id="0" name="Left"><Layout name="Left_Center_Single" Number="0" Position="[[0.5, 0.25, 0.5, 0.5]]" Uniformity="2"><Entity bbox="[0.5, 0.25, 0.5, 0.5]" real_bbox="[0.5, 0.25, 0.3687, 0.3687]" mask="[8036,1,8039,2,8042,2,8046,1,8194,15,8351,21,8508,27,8667,29,8824,1,8826,31,8858,1,8983,37,9142,39,9301,41,9460,43,9619,45,9778,47,9937,49,10096,51,10257,49,10416,51,10575,53,10734,55,10894,55,11054,55,11213,57,11373,57,11533,57,11692,59,11852,59,12011,61,12172,59,12332,59,12491,61,12651,61,12812,59,12971,61,13131,61,13292,59,13452,59,13611,61,13772,59,13932,59,14093,57,14253,57,14413,57,14574,55,14734,55,14894,55,15055,53,15216,51,15377,49,15536,51,15697,49,15858,47,16019,45,16180,43,16341,41,16502,39,16663,37,16824,1,16826,31,16858,1,16987,29,17148,27,17311,21,17474,15,17636,1,17639,2,17642,2,17646,1]" Type="5" Size="3" Color="1" Angle="6" /></Layout></Component><Component id="1" name="Right"><Layout name="Right_Center_Single" Number="0" Position="[[0.5, 0.75, 0.5, 0.5]]" Uniformity="3"><Entity bbox="[0.5, 0.75, 0.5, 0.5]" real_bbox="[0.489, 0.761, 0.4386, 0.4386]" mask="[7006,2,7164,5,7321,1,7323,7,7480,11,7638,14,7795,1,7797,16,7954,20,8112,23,8271,25,8429,28,8586,1,8588,30,8745,34,8903,37,9060,41,9219,43,9377,46,9534,50,9692,53,9851,55,10009,58,10168,60,10327,62,10487,63,10648,63,10808,64,10968,65,11128,66,11289,66,11448,68,11609,68,11769,69,11929,70,12090,69,12249,69,12409,69,12570,67,12729,67,12890,67,13050,66,13210,65,13370,65,13530,64,13691,62,13851,63,14010,63,14171,61,14331,61,14492,59,14652,58,14811,59,14972,57,15132,56,15292,57,15452,56,15612,55,15773,54,15933,53,16093,53,16253,53,16413,52,16574,50,16733,51,16894,49,17054,49,17215,48,17377,1,17379,43,17544,38,17709,1,17712,29,17874,1,17877,23,18042,1,18044,2,18047,13,18210,1,18212,7,18376,2]" Type="3" Size="5" Color="5" Angle="6" /></Layout></Component></Struct></Panel><Panel><Struct name="Left_Right"><Component id="0" name="Left"><Layout name="Left_Center_Single" Number="0" Position="[[0.5, 0.25, 0.5, 0.5]]" Uniformity="2"><Entity bbox="[0.5, 0.25, 0.5, 0.5]" real_bbox="[0.5, 0.25, 0.2662, 0.2662]" mask="[9480,3,9639,5,9798,7,9957,9,10116,11,10275,13,10434,15,10593,17,10752,19,10911,21,11070,23,11229,25,11388,27,11547,29,11706,31,11865,33,12024,35,12183,37,12342,39,12501,41,12660,43,12820,43,12980,43,13141,41,13302,39,13463,37,13624,35,13785,33,13946,31,14107,29,14268,27,14429,25,14590,23,14751,21,14912,19,15073,17,15234,15,15395,13,15556,11,15717,9,15878,7,16039,5,16200,3]" Type="2" Size="1" Color="8" Angle="6" /></Layout></Component><Component id="1" name="Right"><Layout name="Right_Center_Single" Number="0" Position="[[0.5, 0.75, 0.5, 0.5]]" Uniformity="3"><Entity bbox="[0.5, 0.75, 0.5, 0.5]" real_bbox="[0.5, 0.75, 0.2574, 0.2574]" mask="[9556,1,9558,1,9715,6,9722,1,9874,13,10033,16,10051,1,10192,22,10351,26,10510,28,10669,29,10828,30,10987,32,11146,33,11305,35,11464,35,11623,36,11782,38,11941,39,12100,41,12261,40,12420,41,12581,40,12741,41,12902,39,13061,41,13222,40,13382,41,13542,40,13702,41,13863,39,14023,38,14184,36,14344,35,14503,35,14664,33,14824,32,14985,30,15145,29,15305,28,15466,26,15629,22,15791,1,15794,16,15956,13,16120,1,16122,6,16284,1,16286,1]" Type="4" Size="1" Color="5" Angle="2" /></Layout></Component></Struct></Panel><Panel><Struct name="Left_Right"><Component id="0" name="Left"><Layout name="Left_Center_Single" Number="0" Position="[[0.5, 0.25, 0.5, 0.5]]" Uniformity="2"><Entity bbox="[0.5, 0.25, 0.5, 0.5]" real_bbox="[0.5, 0.25, 0.3016, 0.3016]" mask="[9000,3,9159,5,9318,7,9477,9,9636,11,9795,13,9954,15,10113,17,10272,19,10431,21,10590,23,10749,25,10908,27,11067,29,11226,31,11385,33,11544,35,11703,37,11862,39,12021,41,12180,43,12339,45,12498,47,12657,49,12817,49,12977,49,13138,47,13299,45,13460,43,13621,41,13782,39,13943,37,14104,35,14265,33,14426,31,14587,29,14748,27,14909,25,15070,23,15231,21,15392,19,15553,17,15714,15,15875,13,16036,11,16197,9,16358,7,16519,5,16680,3]" Type="2" Size="2" Color="8" Angle="6" /></Layout></Component><Component id="1" name="Right"><Layout name="Right_Center_Single" Number="0" Position="[[0.5, 0.75, 0.5, 0.5]]" Uniformity="3"><Entity bbox="[0.5, 0.75, 0.5, 0.5]" real_bbox="[0.5, 0.75, 0.3016, 0.3016]" mask="[8915,1,9074,6,9233,11,9392,14,9407,1,9551,21,9710,25,9736,1,9869,30,10028,32,10187,34,10346,35,10505,37,10664,37,10823,39,10982,40,11141,41,11300,43,11459,44,11618,45,11777,46,11936,48,12097,46,12257,47,12417,47,12577,48,12738,47,12898,47,13058,47,13218,48,13379,47,13539,47,13700,46,13859,48,14020,46,14180,45,14340,44,14500,43,14661,41,14821,40,14981,39,15142,37,15301,37,15462,35,15622,34,15783,32,15944,30,16106,1,16108,25,16271,21,16435,1,16437,14,16599,11,16763,6,16927,1]" Type="4" Size="2" Color="8" Angle="2" /></Layout></Component></Struct></Panel><Panel><Struct name="Left_Right"><Component id="0" name="Left"><Layout name="Left_Center_Single" Number="0" Position="[[0.5, 0.25, 0.5, 0.5]]" Uniformity="2"><Entity bbox="[0.5, 0.25, 0.5, 0.5]" real_bbox="[0.5, 0.25, 0.3546, 0.3546]" mask="[8360,3,8519,5,8678,7,8837,9,8996,11,9155,13,9314,15,9473,17,9632,19,9791,21,9950,23,10109,25,10268,27,10427,29,10586,31,10745,33,10904,35,11063,37,11222,39,11381,41,11540,43,11699,45,11858,47,12017,49,12176,51,12335,53,12494,55,12653,57,12813,57,12973,57,13134,55,13295,53,13456,51,13617,49,13778,47,13939,45,14100,43,14261,41,14422,39,14583,37,14744,35,14905,33,15066,31,15227,29,15388,27,15549,25,15710,23,15871,21,16032,19,16193,17,16354,15,16515,13,16676,11,16837,9,16998,7,17159,5,17320,3]" Type="2" Size="3" Color="8" Angle="6" /></Layout></Component><Component id="1" name="Right"><Layout name="Right_Center_Single" Number="0" Position="[[0.5, 0.75, 0.5, 0.5]]" Uniformity="3"><Entity bbox="[0.5, 0.75, 0.5, 0.5]" real_bbox="[0.5, 0.75, 0.3988, 0.3988]" mask="[7793,3,7797,1,7952,8,7961,1,8111,13,8270,19,8429,23,8588,27,8616,1,8747,32,8780,1,8906,37,8944,1,9065,41,9224,43,9383,43,9542,45,9701,46,9860,48,10019,48,10178,50,10337,51,10496,53,10655,53,10814,55,10973,56,11132,57,11291,59,11450,60,11609,61,11769,62,11929,62,12090,61,12249,62,12410,61,12570,62,12731,61,12890,63,13051,61,13211,62,13372,61,13532,62,13692,61,13852,62,14012,62,14173,61,14333,60,14493,59,14654,57,14814,56,14974,55,15135,53,15294,53,15455,51,15615,50,15776,48,15935,48,16096,46,16256,45,16417,43,16576,43,16737,41,16898,1,16900,37,17062,1,17064,32,17226,1,17228,27,17391,23,17554,19,17719,13,17881,1,17883,8,18045,1,18047,3]" Type="4" Size="4" Color="1" Angle="2" /></Layout></Component></Struct></Panel><Panel><Struct name="Left_Right"><Component id="0" name="Left"><Layout name="Left_Center_Single" Number="0" Position="[[0.5, 0.25, 0.5, 0.5]]" Uniformity="2"><Entity bbox="[0.5, 0.25, 0.5, 0.5]" real_bbox="[0.5, 0.25, 0.2688, 0.3188]" mask="[9468,27,9628,27,9787,29,9946,31,10106,31,10265,33,10425,33,10584,35,10743,37,10903,37,11062,39,11222,39,11381,41,11540,43,11700,43,11859,45,12019,45,12178,47,12337,49,12497,49,12656,51,12816,51,12976,51,13137,49,13297,49,13458,47,13619,45,13779,45,13940,43,14100,43,14261,41,14422,39,14582,39,14743,37,14903,37,15064,35,15225,33,15385,33,15546,31,15706,31,15867,29,16028,27,16188,27]" Type="4" Size="2" Color="4" Angle="5" /></Layout></Component><Component id="1" name="Right"><Layout name="Right_Center_Single" Number="0" Position="[[0.5, 0.75, 0.5, 0.5]]" Uniformity="3"><Entity bbox="[0.5, 0.75, 0.5, 0.5]" real_bbox="[0.5, 0.75, 0.3188, 0.3188]" mask="[8756,1,8759,1,8761,3,8766,1,8914,15,9070,23,9229,25,9388,27,9546,31,9705,33,9864,35,10023,37,10182,39,10341,41,10500,43,10660,43,10819,45,10978,47,11137,49,11297,49,11457,49,11617,49,11776,51,11936,51,12095,53,12256,51,12416,51,12575,53,12735,52,12895,53,13055,52,13215,53,13376,51,13536,51,13695,53,13856,51,14016,51,14177,49,14337,49,14497,49,14657,49,14818,47,14979,45,15140,43,15300,43,15461,41,15622,39,15783,37,15944,35,16105,33,16266,31,16428,27,16589,25,16750,23,16914,15,17076,1,17079,1,17081,3,17086,1]" Type="5" Size="2" Color="1" Angle="4" /></Layout></Component></Struct></Panel><Panel><Struct name="Left_Right"><Component id="0" name="Left"><Layout name="Left_Center_Single" Number="0" Position="[[0.5, 0.25, 0.5, 0.5]]" Uniformity="2"><Entity bbox="[0.5, 0.25, 0.5, 0.5]" real_bbox="[0.5, 0.25, 0.3187, 0.3688]" mask="[8826,31,8986,31,9145,33,9304,35,9464,35,9623,37,9783,37,9942,39,10101,41,10261,41,10420,43,10580,43,10739,45,10899,45,11058,47,11217,49,11377,49,11536,51,11696,51,11855,53,12014,55,12174,55,12333,57,12493,57,12652,59,12812,59,12972,59,13133,57,13293,57,13454,55,13614,55,13775,53,13936,51,14096,51,14257,49,14417,49,14578,47,14739,45,14899,45,15060,43,15220,43,15381,41,15541,41,15702,39,15863,37,16023,37,16184,35,16344,35,16505,33,16666,31,16826,31]" Type="4" Size="3" Color="4" Angle="5" /></Layout></Component><Component id="1" name="Right"><Layout name="Right_Center_Single" Number="0" Position="[[0.5, 0.75, 0.5, 0.5]]" Uniformity="3"><Entity bbox="[0.5, 0.75, 0.5, 0.5]" real_bbox="[0.5, 0.75, 0.2188, 0.2188]" mask="[10037,2,10041,1,10044,2,10194,15,10352,18,10511,21,10670,23,10829,25,10988,27,11147,29,11306,31,11466,32,11625,33,11784,35,11944,35,12104,35,12263,37,12423,37,12584,35,12744,35,12903,37,13064,35,13224,35,13383,37,13543,37,13704,35,13864,35,14024,35,14185,33,14346,32,14506,31,14667,29,14828,27,14989,25,15150,23,15311,21,15472,18,15634,15,15797,2,15801,1,15804,2]" Type="5" Size="0" Color="5" Angle="4" /></Layout></Component></Struct></Panel><Panel><Struct name="Left_Right"><Component id="0" name="Left"><Layout name="Left_Center_Single" Number="0" Position="[[0.5, 0.25, 0.5, 0.5]]" Uniformity="2"><Entity bbox="[0.5, 0.25, 0.5, 0.5]" real_bbox="[0.5, 0.25, 0.3562, 0.4188]" mask="[8344,35,8504,35,8663,37,8822,39,8982,39,9141,41,9301,41,9460,43,9619,45,9779,45,9938,47,10098,47,10257,49,10416,51,10576,51,10735,53,10895,53,11054,55,11213,57,11373,57,11532,59,11692,59,11851,61,12011,61,12170,63,12329,65,12489,65,12648,67,12808,67,12968,67,13129,65,13289,65,13450,63,13611,61,13771,61,13932,59,14092,59,14253,57,14413,57,14574,55,14735,53,14895,53,15056,51,15216,51,15377,49,15538,47,15698,47,15859,45,16019,45,16180,43,16341,41,16501,41,16662,39,16822,39,16983,37,17144,35,17304,35]" Type="4" Size="4" Color="4" Angle="5" /></Layout></Component><Component id="1" name="Right"><Layout name="Right_Center_Single" Number="0" Position="[[0.5, 0.75, 0.5, 0.5]]" Uniformity="3"><Entity bbox="[0.5, 0.75, 0.5, 0.5]" real_bbox="[0.5, 0.75, 0.3687, 0.3687]" mask="[8116,1,8119,2,8122,2,8126,1,8274,15,8431,21,8588,27,8747,29,8904,1,8906,31,8938,1,9063,37,9222,39,9381,41,9540,43,9699,45,9858,47,10017,49,10176,51,10337,49,10496,51,10655,53,10814,55,10974,55,11134,55,11293,57,11453,57,11613,57,11772,59,11932,59,12091,61,12252,59,12412,59,12571,61,12731,61,12892,59,13051,61,13211,61,13372,59,13532,59,13691,61,13852,59,14012,59,14173,57,14333,57,14493,57,14654,55,14814,55,14974,55,15135,53,15296,51,15457,49,15616,51,15777,49,15938,47,16099,45,16260,43,16421,41,16582,39,16743,37,16904,1,16906,31,16938,1,17067,29,17228,27,17391,21,17554,15,17716,1,17719,2,17722,2,17726,1]" Type="5" Size="3" Color="8" Angle="4" /></Layout></Component></Struct></Panel><Panel><Struct name="Left_Right"><Component id="0" name="Left"><Layout name="Left_Center_Single" Number="0" Position="[[0.5, 0.25, 0.5, 0.5]]" Uniformity="2"><Entity bbox="[0.5, 0.25, 0.5, 0.5]" real_bbox="[0.5, 0.25, 0.3562, 0.4188]" mask="[8344,35,8504,35,8663,37,8822,39,8982,39,9141,41,9301,41,9460,43,9619,45,9779,45,9938,47,10098,47,10257,49,10416,51,10576,51,10735,53,10895,53,11054,55,11213,57,11373,57,11532,59,11692,59,11851,61,12011,61,12170,63,12329,65,12489,65,12648,67,12808,67,12968,67,13129,65,13289,65,13450,63,13611,61,13771,61,13932,59,14092,59,14253,57,14413,57,14574,55,14735,53,14895,53,15056,51,15216,51,15377,49,15538,47,15698,47,15859,45,16019,45,16180,43,16341,41,16501,41,16662,39,16822,39,16983,37,17144,35,17304,35]" Type="4" Size="4" Color="4" Angle="5" /></Layout></Component><Component id="1" name="Right"><Layout name="Right_Center_Single" Number="0" Position="[[0.5, 0.75, 0.5, 0.5]]" Uniformity="3"><Entity bbox="[0.5, 0.75, 0.5, 0.5]" real_bbox="[0.5, 0.75, 0.2188, 0.2188]" mask="[10037,2,10041,1,10044,2,10194,15,10352,18,10511,21,10670,23,10829,25,10988,27,11147,29,11306,31,11466,32,11625,33,11784,35,11944,35,12104,35,12263,37,12423,37,12584,35,12744,35,12903,37,13064,35,13224,35,13383,37,13543,37,13704,35,13864,35,14024,35,14185,33,14346,32,14506,31,14667,29,14828,27,14989,25,15150,23,15311,21,15472,18,15634,15,15797,2,15801,1,15804,2]" Type="5" Size="0" Color="8" Angle="4" /></Layout></Component></Struct></Panel><Panel><Struct name="Left_Right"><Component id="0" name="Left"><Layout name="Left_Center_Single" Number="0" Position="[[0.5, 0.25, 0.5, 0.5]]" Uniformity="2"><Entity bbox="[0.5, 0.25, 0.5, 0.5]" real_bbox="[0.5, 0.2281, 0.3938, 0.375]" mask="[7871,3,8030,7,8190,9,8349,13,8508,17,8667,21,8827,24,8986,28,9145,31,9304,35,9464,38,9623,42,9782,45,9941,47,10100,48,10260,48,10419,49,10578,50,10737,51,10897,51,11056,52,11215,53,11374,54,11534,54,11693,55,11852,56,12011,57,12171,57,12330,58,12489,59,12648,60,12808,60,12968,60,13129,59,13290,58,13451,57,13611,57,13772,56,13933,55,14094,54,14254,54,14415,53,14576,52,14737,51,14897,51,15058,50,15219,49,15380,48,15540,48,15701,47,15862,45,16023,42,16184,38,16344,35,16505,31,16666,28,16827,24,16987,21,17148,17,17309,13,17470,9,17630,7,17791,3]" Type="3" Size="4" Color="4" Angle="5" /></Layout></Component><Component id="1" name="Right"><Layout name="Right_Center_Single" Number="0" Position="[[0.5, 0.75, 0.5, 0.5]]" Uniformity="3"><Entity bbox="[0.5, 0.75, 0.5, 0.5]" real_bbox="[0.5, 0.75, 0.3687, 0.3687]" mask="[8116,1,8119,2,8122,2,8126,1,8274,15,8431,21,8588,27,8747,29,8904,1,8906,31,8938,1,9063,37,9222,39,9381,41,9540,43,9699,45,9858,47,10017,49,10176,51,10337,49,10496,51,10655,53,10814,55,10974,55,11134,55,11293,57,11453,57,11613,57,11772,59,11932,59,12091,61,12252,59,12412,59,12571,61,12731,61,12892,59,13051,61,13211,61,13372,59,13532,59,13691,61,13852,59,14012,59,14173,57,14333,57,14493,57,14654,55,14814,55,14974,55,15135,53,15296,51,15457,49,15616,51,15777,49,15938,47,16099,45,16260,43,16421,41,16582,39,16743,37,16904,1,16906,31,16938,1,17067,29,17228,27,17391,21,17554,15,17716,1,17719,2,17722,2,17726,1]" Type="5" Size="3" Color="8" Angle="4" /></Layout></Component></Struct></Panel><Panel><Struct name="Left_Right"><Component id="0" name="Left"><Layout name="Left_Center_Single" Number="0" Position="[[0.5, 0.25, 0.5, 0.5]]" Uniformity="2"><Entity bbox="[0.5, 0.25, 0.5, 0.5]" real_bbox="[0.5, 0.25, 0.3562, 0.4188]" mask="[8344,35,8504,35,8663,37,8822,39,8982,39,9141,41,9301,41,9460,43,9619,45,9779,45,9938,47,10098,47,10257,49,10416,51,10576,51,10735,53,10895,53,11054,55,11213,57,11373,57,11532,59,11692,59,11851,61,12011,61,12170,63,12329,65,12489,65,12648,67,12808,67,12968,67,13129,65,13289,65,13450,63,13611,61,13771,61,13932,59,14092,59,14253,57,14413,57,14574,55,14735,53,14895,53,15056,51,15216,51,15377,49,15538,47,15698,47,15859,45,16019,45,16180,43,16341,41,16501,41,16662,39,16822,39,16983,37,17144,35,17304,35]" Type="4" Size="4" Color="3" Angle="5" /></Layout></Component><Component id="1" name="Right"><Layout name="Right_Center_Single" Number="0" Position="[[0.5, 0.75, 0.5, 0.5]]" Uniformity="3"><Entity bbox="[0.5, 0.75, 0.5, 0.5]" real_bbox="[0.5, 0.75, 0.3687, 0.3687]" mask="[8116,1,8119,2,8122,2,8126,1,8274,15,8431,21,8588,27,8747,29,8904,1,8906,31,8938,1,9063,37,9222,39,9381,41,9540,43,9699,45,9858,47,10017,49,10176,51,10337,49,10496,51,10655,53,10814,55,10974,55,11134,55,11293,57,11453,57,11613,57,11772,59,11932,59,12091,61,12252,59,12412,59,12571,61,12731,61,12892,59,13051,61,13211,61,13372,59,13532,59,13691,61,13852,59,14012,59,14173,57,14333,57,14493,57,14654,55,14814,55,14974,55,15135,53,15296,51,15457,49,15616,51,15777,49,15938,47,16099,45,16260,43,16421,41,16582,39,16743,37,16904,1,16906,31,16938,1,17067,29,17228,27,17391,21,17554,15,17716,1,17719,2,17722,2,17726,1]" Type="5" Size="3" Color="8" Angle="4" /></Layout></Component></Struct></Panel><Panel><Struct name="Left_Right"><Component id="0" name="Left"><Layout name="Left_Center_Single" Number="0" Position="[[0.5, 0.25, 0.5, 0.5]]" Uniformity="2"><Entity bbox="[0.5, 0.25, 0.5, 0.5]" real_bbox="[0.5, 0.25, 0.3562, 0.4188]" mask="[8344,35,8504,35,8663,37,8822,39,8982,39,9141,41,9301,41,9460,43,9619,45,9779,45,9938,47,10098,47,10257,49,10416,51,10576,51,10735,53,10895,53,11054,55,11213,57,11373,57,11532,59,11692,59,11851,61,12011,61,12170,63,12329,65,12489,65,12648,67,12808,67,12968,67,13129,65,13289,65,13450,63,13611,61,13771,61,13932,59,14092,59,14253,57,14413,57,14574,55,14735,53,14895,53,15056,51,15216,51,15377,49,15538,47,15698,47,15859,45,16019,45,16180,43,16341,41,16501,41,16662,39,16822,39,16983,37,17144,35,17304,35]" Type="4" Size="4" Color="8" Angle="5" /></Layout></Component><Component id="1" name="Right"><Layout name="Right_Center_Single" Number="0" Position="[[0.5, 0.75, 0.5, 0.5]]" Uniformity="3"><Entity bbox="[0.5, 0.75, 0.5, 0.5]" real_bbox="[0.5, 0.75, 0.3687, 0.3687]" mask="[8116,1,8119,2,8122,2,8126,1,8274,15,8431,21,8588,27,8747,29,8904,1,8906,31,8938,1,9063,37,9222,39,9381,41,9540,43,9699,45,9858,47,10017,49,10176,51,10337,49,10496,51,10655,53,10814,55,10974,55,11134,55,11293,57,11453,57,11613,57,11772,59,11932,59,12091,61,12252,59,12412,59,12571,61,12731,61,12892,59,13051,61,13211,61,13372,59,13532,59,13691,61,13852,59,14012,59,14173,57,14333,57,14493,57,14654,55,14814,55,14974,55,15135,53,15296,51,15457,49,15616,51,15777,49,15938,47,16099,45,16260,43,16421,41,16582,39,16743,37,16904,1,16906,31,16938,1,17067,29,17228,27,17391,21,17554,15,17716,1,17719,2,17722,2,17726,1]" Type="5" Size="3" Color="8" Angle="4" /></Layout></Component></Struct></Panel><Panel><Struct name="Left_Right"><Component id="0" name="Left"><Layout name="Left_Center_Single" Number="0" Position="[[0.5, 0.25, 0.5, 0.5]]" Uniformity="2"><Entity bbox="[0.5, 0.25, 0.5, 0.5]" real_bbox="[0.5, 0.25, 0.3562, 0.4188]" mask="[8344,35,8504,35,8663,37,8822,39,8982,39,9141,41,9301,41,9460,43,9619,45,9779,45,9938,47,10098,47,10257,49,10416,51,10576,51,10735,53,10895,53,11054,55,11213,57,11373,57,11532,59,11692,59,11851,61,12011,61,12170,63,12329,65,12489,65,12648,67,12808,67,12968,67,13129,65,13289,65,13450,63,13611,61,13771,61,13932,59,14092,59,14253,57,14413,57,14574,55,14735,53,14895,53,15056,51,15216,51,15377,49,15538,47,15698,47,15859,45,16019,45,16180,43,16341,41,16501,41,16662,39,16822,39,16983,37,17144,35,17304,35]" Type="4" Size="4" Color="4" Angle="5" /></Layout></Component><Component id="1" name="Right"><Layout name="Right_Center_Single" Number="0" Position="[[0.5, 0.75, 0.5, 0.5]]" Uniformity="3"><Entity bbox="[0.5, 0.75, 0.5, 0.5]" real_bbox="[0.5, 0.75, 0.3687, 0.3687]" mask="[8116,1,8119,2,8122,2,8126,1,8274,15,8431,21,8588,27,8747,29,8904,1,8906,31,8938,1,9063,37,9222,39,9381,41,9540,43,9699,45,9858,47,10017,49,10176,51,10337,49,10496,51,10655,53,10814,55,10974,55,11134,55,11293,57,11453,57,11613,57,11772,59,11932,59,12091,61,12252,59,12412,59,12571,61,12731,61,12892,59,13051,61,13211,61,13372,59,13532,59,13691,61,13852,59,14012,59,14173,57,14333,57,14493,57,14654,55,14814,55,14974,55,15135,53,15296,51,15457,49,15616,51,15777,49,15938,47,16099,45,16260,43,16421,41,16582,39,16743,37,16904,1,16906,31,16938,1,17067,29,17228,27,17391,21,17554,15,17716,1,17719,2,17722,2,17726,1]" Type="5" Size="3" Color="7" Angle="4" /></Layout></Component></Struct></Panel><Panel><Struct name="Left_Right"><Component id="0" name="Left"><Layout name="Left_Center_Single" Number="0" Position="[[0.5, 0.25, 0.5, 0.5]]" Uniformity="2"><Entity bbox="[0.5, 0.25, 0.5, 0.5]" real_bbox="[0.5, 0.25, 0.3562, 0.4188]" mask="[8344,35,8504,35,8663,37,8822,39,8982,39,9141,41,9301,41,9460,43,9619,45,9779,45,9938,47,10098,47,10257,49,10416,51,10576,51,10735,53,10895,53,11054,55,11213,57,11373,57,11532,59,11692,59,11851,61,12011,61,12170,63,12329,65,12489,65,12648,67,12808,67,12968,67,13129,65,13289,65,13450,63,13611,61,13771,61,13932,59,14092,59,14253,57,14413,57,14574,55,14735,53,14895,53,15056,51,15216,51,15377,49,15538,47,15698,47,15859,45,16019,45,16180,43,16341,41,16501,41,16662,39,16822,39,16983,37,17144,35,17304,35]" Type="4" Size="4" Color="4" Angle="5" /></Layout></Component><Component id="1" name="Right"><Layout name="Right_Center_Single" Number="0" Position="[[0.5, 0.75, 0.5, 0.5]]" Uniformity="3"><Entity bbox="[0.5, 0.75, 0.5, 0.5]" real_bbox="[0.5, 0.75, 0.4188, 0.4188]" mask="[7477,4,7482,4,7632,19,7790,23,7947,29,8105,33,8264,35,8421,41,8580,43,8739,45,8898,47,9057,49,9216,51,9375,53,9534,55,9693,57,9853,57,10013,57,10172,59,10331,61,10491,61,10650,63,10810,63,10970,63,11129,65,11289,65,11448,67,11608,67,11768,67,11928,67,12088,67,12247,69,12407,69,12567,69,12727,69,12888,67,13047,69,13207,69,13367,69,13527,69,13688,67,13848,67,14008,67,14168,67,14328,67,14489,65,14649,65,14810,63,14970,63,15130,63,15291,61,15451,61,15612,59,15773,57,15933,57,16093,57,16254,55,16415,53,16576,51,16737,49,16898,47,17059,45,17220,43,17381,41,17544,35,17705,33,17867,29,18030,23,18192,19,18357,4,18362,4]" Type="5" Size="4" Color="8" Angle="4" /></Layout></Component></Struct></Panel><Panel><Struct name="Left_Right"><Component id="0" name="Left"><Layout name="Left_Center_Single" Number="0" Position="[[0.5, 0.25, 0.5, 0.5]]" Uniformity="2"><Entity bbox="[0.5, 0.25, 0.5, 0.5]" real_bbox="[0.5, 0.25, 0.3562, 0.4188]" mask="[8344,35,8504,35,8663,37,8822,39,8982,39,9141,41,9301,41,9460,43,9619,45,9779,45,9938,47,10098,47,10257,49,10416,51,10576,51,10735,53,10895,53,11054,55,11213,57,11373,57,11532,59,11692,59,11851,61,12011,61,12170,63,12329,65,12489,65,12648,67,12808,67,12968,67,13129,65,13289,65,13450,63,13611,61,13771,61,13932,59,14092,59,14253,57,14413,57,14574,55,14735,53,14895,53,15056,51,15216,51,15377,49,15538,47,15698,47,15859,45,16019,45,16180,43,16341,41,16501,41,16662,39,16822,39,16983,37,17144,35,17304,35]" Type="4" Size="4" Color="0" Angle="5" /></Layout></Component><Component id="1" name="Right"><Layout name="Right_Center_Single" Number="0" Position="[[0.5, 0.75, 0.5, 0.5]]" Uniformity="3"><Entity bbox="[0.5, 0.75, 0.5, 0.5]" real_bbox="[0.5, 0.75, 0.3687, 0.3687]" mask="[8116,1,8119,2,8122,2,8126,1,8274,15,8431,21,8588,27,8747,29,8904,1,8906,31,8938,1,9063,37,9222,39,9381,41,9540,43,9699,45,9858,47,10017,49,10176,51,10337,49,10496,51,10655,53,10814,55,10974,55,11134,55,11293,57,11453,57,11613,57,11772,59,11932,59,12091,61,12252,59,12412,59,12571,61,12731,61,12892,59,13051,61,13211,61,13372,59,13532,59,13691,61,13852,59,14012,59,14173,57,14333,57,14493,57,14654,55,14814,55,14974,55,15135,53,15296,51,15457,49,15616,51,15777,49,15938,47,16099,45,16260,43,16421,41,16582,39,16743,37,16904,1,16906,31,16938,1,17067,29,17228,27,17391,21,17554,15,17716,1,17719,2,17722,2,17726,1]" Type="5" Size="3" Color="8" Angle="4" /></Layout></Component></Struct></Panel></Panels><Rules><Rule_Group id="0"><Rule name="Constant" attr="Number/Position" /><Rule name="Constant" attr="Type" /><Rule name="Progression" attr="Size" /><Rule name="Constant" attr="Color" /></Rule_Group><Rule_Group id="1"><Rule name="Constant" attr="Number/Position" /><Rule name="Constant" attr="Type" /><Rule name="Arithmetic" attr="Size" /><Rule name="Distribute_Three" attr="Color" /></Rule_Group></Rules></Data>