<Data><Panels><Panel><Struct name="Out_In"><Component id="0" name="Out"><Layout name="Out_Center_Single" Number="0" Position="[[0.5, 0.5, 1, 1]]" Uniformity="0"><Entity bbox="[0.5, 0.5, 1, 1]" real_bbox="[0.3875, 0.5, 0.6938, 0.7938]" mask="[1201,1,1360,3,1520,3,1679,5,1838,7,1998,7,2157,9,2317,9,2476,11,2636,11,2795,13,2954,15,3114,15,3273,17,3433,17,3592,19,3752,19,3911,21,4070,23,4230,23,4389,25,4549,25,4708,27,4868,27,5027,29,5186,31,5346,31,5505,33,5665,33,5824,35,5983,37,6143,37,6302,39,6462,39,6621,41,6781,41,6940,43,7099,45,7259,45,7418,47,7578,47,7737,49,7897,49,8056,51,8215,53,8375,53,8534,55,8694,55,8853,57,9013,57,9172,59,9331,61,9491,61,9650,63,9810,63,9969,65,10129,65,10288,67,10447,69,10607,69,10766,71,10926,71,11085,73,11245,73,11404,75,11563,77,11723,77,11882,79,12042,79,12201,81,12361,81,12520,83,12679,85,12839,85,12998,87,13158,87,13317,89,13477,89,13636,91,13795,93,13955,93,14114,95,14274,95,14433,97,14592,99,14752,99,14911,101,15071,101,15230,103,15390,103,15549,105,15708,107,15868,107,16027,109,16187,109,16346,111,16506,111,16665,113,16824,115,16984,115,17143,117,17303,117,17462,119,17622,119,17781,121,17940,123,18100,123,18259,125,18419,125,18578,127,18739,125]" Type="1" Size="5" Color="0" Angle="3" /></Layout></Component><Component id="1" name="In"><Layout name="In_Center_Single" Number="0" Position="[[0.5, 0.5, 0.33, 0.33]]" Uniformity="3"><Entity bbox="[0.5, 0.5, 0.33, 0.33]" real_bbox="[0.4656, 0.5, 0.2125, 0.2438]" mask="[9360,3,9520,3,9679,5,9838,7,9998,7,10157,9,10317,9,10476,11,10635,13,10795,13,10954,15,11114,15,11273,17,11433,17,11592,19,11751,21,11911,21,12070,23,12230,23,12389,25,12549,25,12708,27,12867,29,13027,29,13186,31,13346,31,13505,33,13664,35,13824,35,13983,37,14143,37,14302,39,14462,39,14623,37]" Type="1" Size="4" Color="3" Angle="3" /></Layout></Component></Struct></Panel><Panel><Struct name="Out_In"><Component id="0" name="Out"><Layout name="Out_Center_Single" Number="0" Position="[[0.5, 0.5, 1, 1]]" Uniformity="0"><Entity bbox="[0.5, 0.5, 1, 1]" real_bbox="[0.4, 0.5, 0.6188, 0.7062]" mask="[2481,1,2640,3,2800,3,2959,5,3118,7,3278,7,3437,9,3597,9,3756,11,3916,11,4075,13,4234,15,4394,15,4553,17,4713,17,4872,19,5032,19,5191,21,5350,23,5510,23,5669,25,5829,25,5988,27,6148,27,6307,29,6466,31,6626,31,6785,33,6945,33,7104,35,7264,35,7423,37,7582,39,7742,39,7901,41,8061,41,8220,43,8380,43,8539,45,8698,47,8858,47,9017,49,9177,49,9336,51,9495,53,9655,53,9814,55,9974,55,10133,57,10293,57,10452,59,10611,61,10771,61,10930,63,11090,63,11249,65,11409,65,11568,67,11727,69,11887,69,12046,71,12206,71,12365,73,12525,73,12684,75,12843,77,13003,77,13162,79,13322,79,13481,81,13641,81,13800,83,13959,85,14119,85,14278,87,14438,87,14597,89,14757,89,14916,91,15075,93,15235,93,15394,95,15554,95,15713,97,15873,97,16032,99,16191,101,16351,101,16510,103,16670,103,16829,105,16989,105,17148,107,17307,109,17467,109,17626,111,17786,111,17945,113,18106,111]" Type="1" Size="4" Color="0" Angle="3" /></Layout></Component><Component id="1" name="In"><Layout name="In_Center_Single" Number="0" Position="[[0.5, 0.5, 0.33, 0.33]]" Uniformity="3"><Entity bbox="[0.5, 0.5, 0.33, 0.33]" real_bbox="[0.4906, 0.5, 0.1875, 0.1938]" mask="[10320,3,10479,5,10638,7,10796,11,10955,13,11114,15,11272,19,11431,21,11590,23,11749,25,11907,29,12066,31,12226,31,12386,31,12547,29,12707,29,12868,27,13028,27,13188,27,13349,25,13509,25,13669,25,13830,23,13990,23,14151,21,14311,21,14471,21,14632,19,14792,19,14953,17]" Type="3" Size="2" Color="3" Angle="3" /></Layout></Component></Struct></Panel><Panel><Struct name="Out_In"><Component id="0" name="Out"><Layout name="Out_Center_Single" Number="0" Position="[[0.5, 0.5, 1, 1]]" Uniformity="0"><Entity bbox="[0.5, 0.5, 1, 1]" real_bbox="[0.4125, 0.5, 0.5438, 0.6188]" mask="[3761,1,3920,3,4080,3,4239,5,4398,7,4558,7,4717,9,4877,9,5036,11,5196,11,5355,13,5514,15,5674,15,5833,17,5993,17,6152,19,6312,19,6471,21,6630,23,6790,23,6949,25,7109,25,7268,27,7428,27,7587,29,7746,31,7906,31,8065,33,8225,33,8384,35,8544,35,8703,37,8862,39,9022,39,9181,41,9341,41,9500,43,9660,43,9819,45,9978,47,10138,47,10297,49,10457,49,10616,51,10776,51,10935,53,11094,55,11254,55,11413,57,11573,57,11732,59,11892,59,12051,61,12210,63,12370,63,12529,65,12689,65,12848,67,13008,67,13167,69,13326,71,13486,71,13645,73,13805,73,13964,75,14124,75,14283,77,14442,79,14602,79,14761,81,14921,81,15080,83,15240,83,15399,85,15558,87,15718,87,15877,89,16037,89,16196,91,16356,91,16515,93,16674,95,16834,95,16993,97,17153,97,17312,99,17473,97]" Type="1" Size="3" Color="0" Angle="3" /></Layout></Component><Component id="1" name="In"><Layout name="In_Center_Single" Number="0" Position="[[0.5, 0.5, 0.33, 0.33]]" Uniformity="3"><Entity bbox="[0.5, 0.5, 0.33, 0.33]" real_bbox="[0.5, 0.5, 0.1508, 0.1508]" mask="[11118,7,11277,10,11434,15,11593,17,11752,19,11912,19,12071,21,12231,21,12390,23,12550,23,12710,23,12870,23,13030,23,13190,23,13350,23,13511,21,13671,21,13832,19,13992,19,14153,17,14314,15,14477,10,14638,7]" Type="5" Size="0" Color="3" Angle="3" /></Layout></Component></Struct></Panel><Panel><Struct name="Out_In"><Component id="0" name="Out"><Layout name="Out_Center_Single" Number="0" Position="[[0.5, 0.5, 1, 1]]" Uniformity="0"><Entity bbox="[0.5, 0.5, 1, 1]" real_bbox="[0.5, 0.5, 0.8142, 0.8142]" mask="[2480,3,2639,5,2798,7,2957,9,3116,11,3275,13,3434,15,3593,17,3752,19,3911,21,4070,23,4229,25,4388,27,4547,29,4706,31,4865,33,5024,35,5183,37,5342,39,5501,41,5660,43,5819,45,5978,47,6137,49,6296,51,6455,53,6614,55,6773,57,6932,59,7091,61,7250,63,7409,65,7568,67,7727,69,7886,71,8045,73,8204,75,8363,77,8522,79,8681,81,8840,83,8999,85,9158,87,9317,89,9476,91,9635,93,9794,95,9953,97,10112,99,10271,101,10430,103,10589,105,10748,107,10907,109,11066,111,11225,113,11384,115,11543,117,11702,119,11861,121,12020,123,12179,125,12338,127,12497,129,12656,131,12816,131,12976,131,13137,129,13298,127,13459,125,13620,123,13781,121,13942,119,14103,117,14264,115,14425,113,14586,111,14747,109,14908,107,15069,105,15230,103,15391,101,15552,99,15713,97,15874,95,16035,93,16196,91,16357,89,16518,87,16679,85,16840,83,17001,81,17162,79,17323,77,17484,75,17645,73,17806,71,17967,69,18128,67,18289,65,18450,63,18611,61,18772,59,18933,57,19094,55,19255,53,19416,51,19577,49,19738,47,19899,45,20060,43,20221,41,20382,39,20543,37,20704,35,20865,33,21026,31,21187,29,21348,27,21509,25,21670,23,21831,21,21992,19,22153,17,22314,15,22475,13,22636,11,22797,9,22958,7,23119,5,23280,3]" Type="2" Size="4" Color="0" Angle="0" /></Layout></Component><Component id="1" name="In"><Layout name="In_Center_Single" Number="0" Position="[[0.5, 0.5, 0.33, 0.33]]" Uniformity="3"><Entity bbox="[0.5, 0.5, 0.33, 0.33]" real_bbox="[0.5375, 0.5, 0.2313, 0.2563]" mask="[10942,39,11101,41,11262,39,11422,39,11583,37,11743,37,11904,35,12064,35,12225,33,12386,31,12546,31,12707,29,12867,29,13028,27,13188,27,13349,25,13510,23,13670,23,13831,21,13991,21,14152,19,14312,19,14473,17,14633,17,14794,15,14955,13,15115,13,15276,11,15436,11,15597,9,15757,9,15918,7,16078,7,16239,5,16400,3,16560,3,16721,1]" Type="1" Size="5" Color="1" Angle="7" /></Layout></Component></Struct></Panel><Panel><Struct name="Out_In"><Component id="0" name="Out"><Layout name="Out_Center_Single" Number="0" Position="[[0.5, 0.5, 1, 1]]" Uniformity="0"><Entity bbox="[0.5, 0.5, 1, 1]" real_bbox="[0.5, 0.5, 0.7082, 0.7082]" mask="[3920,3,4079,5,4238,7,4397,9,4556,11,4715,13,4874,15,5033,17,5192,19,5351,21,5510,23,5669,25,5828,27,5987,29,6146,31,6305,33,6464,35,6623,37,6782,39,6941,41,7100,43,7259,45,7418,47,7577,49,7736,51,7895,53,8054,55,8213,57,8372,59,8531,61,8690,63,8849,65,9008,67,9167,69,9326,71,9485,73,9644,75,9803,77,9962,79,10121,81,10280,83,10439,85,10598,87,10757,89,10916,91,11075,93,11234,95,11393,97,11552,99,11711,101,11870,103,12029,105,12188,107,12347,109,12506,111,12665,113,12825,113,12985,113,13146,111,13307,109,13468,107,13629,105,13790,103,13951,101,14112,99,14273,97,14434,95,14595,93,14756,91,14917,89,15078,87,15239,85,15400,83,15561,81,15722,79,15883,77,16044,75,16205,73,16366,71,16527,69,16688,67,16849,65,17010,63,17171,61,17332,59,17493,57,17654,55,17815,53,17976,51,18137,49,18298,47,18459,45,18620,43,18781,41,18942,39,19103,37,19264,35,19425,33,19586,31,19747,29,19908,27,20069,25,20230,23,20391,21,20552,19,20713,17,20874,15,21035,13,21196,11,21357,9,21518,7,21679,5,21840,3]" Type="2" Size="3" Color="0" Angle="0" /></Layout></Component><Component id="1" name="In"><Layout name="In_Center_Single" Number="0" Position="[[0.5, 0.5, 0.33, 0.33]]" Uniformity="3"><Entity bbox="[0.5, 0.5, 0.33, 0.33]" real_bbox="[0.5125, 0.5, 0.2188, 0.2312]" mask="[10471,21,10630,23,10790,23,10949,25,11109,25,11269,25,11428,27,11588,27,11747,29,11907,29,12067,29,12226,31,12386,31,12546,31,12705,33,12865,33,13025,33,13184,35,13344,35,13503,37,13663,37,13823,37,13984,35,14146,31,14307,29,14468,27,14630,23,14791,21,14952,19,15114,15,15275,13,15436,11,15597,9,15759,5,15920,3]" Type="3" Size="3" Color="1" Angle="7" /></Layout></Component></Struct></Panel><Panel><Struct name="Out_In"><Component id="0" name="Out"><Layout name="Out_Center_Single" Number="0" Position="[[0.5, 0.5, 1, 1]]" Uniformity="0"><Entity bbox="[0.5, 0.5, 1, 1]" real_bbox="[0.5, 0.5, 0.9026, 0.9026]" mask="[1360,3,1519,5,1678,7,1837,9,1996,11,2155,13,2314,15,2473,17,2632,19,2791,21,2950,23,3109,25,3268,27,3427,29,3586,31,3745,33,3904,35,4063,37,4222,39,4381,41,4540,43,4699,45,4858,47,5017,49,5176,51,5335,53,5494,55,5653,57,5812,59,5971,61,6130,63,6289,65,6448,67,6607,69,6766,71,6925,73,7084,75,7243,77,7402,79,7561,81,7720,83,7879,85,8038,87,8197,89,8356,91,8515,93,8674,95,8833,97,8992,99,9151,101,9310,103,9469,105,9628,107,9787,109,9946,111,10105,113,10264,115,10423,117,10582,119,10741,121,10900,123,11059,125,11218,127,11377,129,11536,131,11695,133,11854,135,12013,137,12172,139,12331,141,12490,143,12649,145,12809,145,12969,145,13130,143,13291,141,13452,139,13613,137,13774,135,13935,133,14096,131,14257,129,14418,127,14579,125,14740,123,14901,121,15062,119,15223,117,15384,115,15545,113,15706,111,15867,109,16028,107,16189,105,16350,103,16511,101,16672,99,16833,97,16994,95,17155,93,17316,91,17477,89,17638,87,17799,85,17960,83,18121,81,18282,79,18443,77,18604,75,18765,73,18926,71,19087,69,19248,67,19409,65,19570,63,19731,61,19892,59,20053,57,20214,55,20375,53,20536,51,20697,49,20858,47,21019,45,21180,43,21341,41,21502,39,21663,37,21824,35,21985,33,22146,31,22307,29,22468,27,22629,25,22790,23,22951,21,23112,19,23273,17,23434,15,23595,13,23756,11,23917,9,24078,7,24239,5,24400,3]" Type="2" Size="5" Color="0" Angle="0" /></Layout></Component><Component id="1" name="In"><Layout name="In_Center_Single" Number="0" Position="[[0.5, 0.5, 0.33, 0.33]]" Uniformity="3"><Entity bbox="[0.5, 0.5, 0.33, 0.33]" real_bbox="[0.5, 0.5, 0.1838, 0.1838]" mask="[10638,7,10796,11,10953,17,11112,19,11272,19,11430,23,11589,25,11749,25,11909,25,12068,27,12228,27,12387,29,12547,29,12707,29,12867,29,13027,29,13187,29,13347,29,13508,27,13668,27,13829,25,13989,25,14149,25,14310,23,14472,19,14632,19,14793,17,14956,11,15118,7]" Type="5" Size="1" Color="1" Angle="7" /></Layout></Component></Struct></Panel><Panel><Struct name="Out_In"><Component id="0" name="Out"><Layout name="Out_Center_Single" Number="0" Position="[[0.5, 0.5, 1, 1]]" Uniformity="0"><Entity bbox="[0.5, 0.5, 1, 1]" real_bbox="[0.4845, 0.5155, 0.6684, 0.6684]" mask="[3929,3,4087,6,4246,8,4404,11,4561,15,4719,18,4876,1,4878,20,5035,24,5193,27,5352,29,5510,32,5667,36,5825,39,5982,1,5984,41,6141,45,6299,48,6456,1,6458,50,6615,54,6773,57,6931,60,7088,64,7247,66,7405,69,7562,73,7720,76,7879,78,8037,81,8194,85,8353,87,8511,90,8670,92,8830,93,8989,95,9150,95,9310,96,9470,97,9630,98,9791,98,9951,99,10111,100,10271,101,10431,102,10592,102,10752,103,10911,105,11072,105,11232,106,11393,105,11553,105,11712,105,11872,105,12033,103,12193,102,12353,102,12513,101,12673,101,12833,101,12994,99,13154,99,13314,98,13475,96,13634,98,13795,96,13955,95,14114,96,14275,94,14435,93,14595,93,14756,91,14915,92,15076,91,15236,90,15396,90,15556,89,15716,88,15877,88,16036,88,16196,87,16357,86,16517,85,16678,83,16837,85,16997,84,17158,82,17318,82,17478,81,17638,81,17798,80,17959,79,18119,79,18279,78,18439,77,18598,78,18759,76,18919,76,19080,75,19239,75,19400,74,19561,1,19563,70,19725,1,19730,62,19895,2,19898,54,20060,2,20063,48,20228,1,20230,41,20393,1,20396,1,20398,33,20561,29,20727,2,20731,18,20893,1,20896,13,21061,7,21225,1]" Type="3" Size="3" Color="0" Angle="6" /></Layout></Component><Component id="1" name="In"><Layout name="In_Center_Single" Number="0" Position="[[0.5, 0.5, 0.33, 0.33]]" Uniformity="3"><Entity bbox="[0.5, 0.5, 0.33, 0.33]" real_bbox="[0.5, 0.4625, 0.2563, 0.2312]" mask="[9692,1,9850,4,10008,6,10166,8,10325,9,10483,11,10641,13,10799,15,10958,16,11116,18,11274,20,11432,22,11590,24,11749,25,11907,27,12065,29,12223,31,12381,33,12540,34,12698,36,12857,37,13018,36,13180,34,13341,33,13503,31,13665,29,13827,27,13989,25,14150,24,14312,22,14474,20,14636,18,14798,16,14959,15,15121,13,15283,11,15445,9,15606,8,15768,6,15930,4,16092,1]" Type="1" Size="5" Color="0" Angle="5" /></Layout></Component></Struct></Panel><Panel><Struct name="Out_In"><Component id="0" name="Out"><Layout name="Out_Center_Single" Number="0" Position="[[0.5, 0.5, 1, 1]]" Uniformity="0"><Entity bbox="[0.5, 0.5, 1, 1]" real_bbox="[0.4779, 0.5221, 0.8584, 0.8584]" mask="[1371,3,1529,6,1686,10,1844,13,2003,15,2161,18,2318,1,2320,20,2477,24,2636,26,2794,29,2951,33,3109,36,3268,38,3426,41,3583,1,3585,43,3742,47,3900,50,4057,54,4215,57,4374,59,4531,63,4689,66,4848,68,5006,71,5163,75,5321,78,5480,80,5637,1,5639,82,5796,86,5954,89,6113,91,6271,94,6428,98,6586,101,6743,1,6745,103,6902,107,7060,110,7219,112,7377,115,7536,117,7696,118,7855,120,8016,120,8176,121,8336,122,8496,123,8657,123,8817,124,8977,125,9137,126,9297,127,9458,127,9618,128,9777,130,9937,131,10098,131,10258,132,10418,133,10578,134,10738,135,10899,135,11059,135,11219,135,11379,134,11539,134,11699,133,11860,132,12020,132,12180,131,12341,130,12500,130,12660,129,12821,128,12980,128,13141,126,13301,127,13461,126,13621,125,13781,124,13942,123,14102,122,14262,122,14422,122,14582,121,14743,120,14902,120,15062,119,15223,118,15383,117,15544,115,15703,117,15863,116,16024,114,16184,114,16344,113,16504,113,16664,113,16824,112,16984,112,17145,110,17305,109,17464,110,17625,109,17785,108,17945,108,18105,107,18265,106,18426,105,18586,104,18746,104,18906,104,19067,102,19227,102,19386,102,19547,100,19707,99,19868,99,20028,98,20187,98,20347,98,20508,96,20668,95,20828,95,20988,94,21149,93,21310,92,21474,2,21478,83,21640,1,21643,78,21807,73,21972,1,21975,64,22142,2,22145,55,22307,2,22310,49,22475,43,22640,1,22642,2,22645,33,22808,29,22974,22,23139,2,23143,13,23308,7,23472,1]" Type="3" Size="5" Color="0" Angle="6" /></Layout></Component><Component id="1" name="In"><Layout name="In_Center_Single" Number="0" Position="[[0.5, 0.5, 0.33, 0.33]]" Uniformity="3"><Entity bbox="[0.5, 0.5, 0.33, 0.33]" real_bbox="[0.5, 0.4875, 0.2312, 0.2187]" mask="[9995,3,10154,6,10314,9,10473,13,10632,17,10791,20,10951,23,11110,26,11269,28,11428,29,11588,29,11747,30,11906,31,12065,32,12224,33,12384,33,12543,34,12702,35,12862,35,13022,35,13183,34,13344,33,13504,33,13665,32,13826,31,13987,30,14148,29,14308,29,14469,28,14630,26,14791,23,14951,20,15112,17,15273,13,15434,9,15594,6,15755,3]" Type="3" Size="3" Color="0" Angle="5" /></Layout></Component></Struct></Panel><Panel><Struct name="Out_In"><Component id="0" name="Out"><Layout name="Out_Center_Single" Number="0" Position="[[0.5, 0.5, 1, 1]]" Uniformity="0"><Entity bbox="[0.5, 0.5, 1, 1]" real_bbox="[0.4779, 0.5221, 0.8584, 0.8584]" mask="[1371,3,1529,6,1686,10,1844,13,2003,15,2161,18,2318,1,2320,20,2477,24,2636,26,2794,29,2951,33,3109,36,3268,38,3426,41,3583,1,3585,43,3742,47,3900,50,4057,54,4215,57,4374,59,4531,63,4689,66,4848,68,5006,71,5163,75,5321,78,5480,80,5637,1,5639,82,5796,86,5954,89,6113,91,6271,94,6428,98,6586,101,6743,1,6745,103,6902,107,7060,110,7219,112,7377,115,7536,117,7696,118,7855,120,8016,120,8176,121,8336,122,8496,123,8657,123,8817,124,8977,125,9137,126,9297,127,9458,127,9618,128,9777,130,9937,131,10098,131,10258,132,10418,133,10578,134,10738,135,10899,135,11059,135,11219,135,11379,134,11539,134,11699,133,11860,132,12020,132,12180,131,12341,130,12500,130,12660,129,12821,128,12980,128,13141,126,13301,127,13461,126,13621,125,13781,124,13942,123,14102,122,14262,122,14422,122,14582,121,14743,120,14902,120,15062,119,15223,118,15383,117,15544,115,15703,117,15863,116,16024,114,16184,114,16344,113,16504,113,16664,113,16824,112,16984,112,17145,110,17305,109,17464,110,17625,109,17785,108,17945,108,18105,107,18265,106,18426,105,18586,104,18746,104,18906,104,19067,102,19227,102,19386,102,19547,100,19707,99,19868,99,20028,98,20187,98,20347,98,20508,96,20668,95,20828,95,20988,94,21149,93,21310,92,21474,2,21478,83,21640,1,21643,78,21807,73,21972,1,21975,64,22142,2,22145,55,22307,2,22310,49,22475,43,22640,1,22642,2,22645,33,22808,29,22974,22,23139,2,23143,13,23308,7,23472,1]" Type="3" Size="5" Color="0" Angle="6" /></Layout></Component><Component id="1" name="In"><Layout name="In_Center_Single" Number="0" Position="[[0.5, 0.5, 0.33, 0.33]]" Uniformity="3"><Entity bbox="[0.5, 0.5, 0.33, 0.33]" real_bbox="[0.5, 0.5, 0.1838, 0.1838]" mask="[10638,7,10796,11,10953,17,11112,19,11272,19,11430,23,11589,25,11749,25,11909,25,12068,27,12228,27,12387,29,12547,29,12707,29,12867,29,13027,29,13187,29,13347,29,13508,27,13668,27,13829,25,13989,25,14149,25,14310,23,14472,19,14632,19,14793,17,14956,11,15118,7]" Type="5" Size="1" Color="0" Angle="5" /></Layout></Component></Struct></Panel><Panel><Struct name="Out_In"><Component id="0" name="Out"><Layout name="Out_Center_Single" Number="0" Position="[[0.5, 0.5, 1, 1]]" Uniformity="0"><Entity bbox="[0.5, 0.5, 1, 1]" real_bbox="[0.4845, 0.5155, 0.6684, 0.6684]" mask="[3929,3,4087,6,4246,8,4404,11,4561,15,4719,18,4876,1,4878,20,5035,24,5193,27,5352,29,5510,32,5667,36,5825,39,5982,1,5984,41,6141,45,6299,48,6456,1,6458,50,6615,54,6773,57,6931,60,7088,64,7247,66,7405,69,7562,73,7720,76,7879,78,8037,81,8194,85,8353,87,8511,90,8670,92,8830,93,8989,95,9150,95,9310,96,9470,97,9630,98,9791,98,9951,99,10111,100,10271,101,10431,102,10592,102,10752,103,10911,105,11072,105,11232,106,11393,105,11553,105,11712,105,11872,105,12033,103,12193,102,12353,102,12513,101,12673,101,12833,101,12994,99,13154,99,13314,98,13475,96,13634,98,13795,96,13955,95,14114,96,14275,94,14435,93,14595,93,14756,91,14915,92,15076,91,15236,90,15396,90,15556,89,15716,88,15877,88,16036,88,16196,87,16357,86,16517,85,16678,83,16837,85,16997,84,17158,82,17318,82,17478,81,17638,81,17798,80,17959,79,18119,79,18279,78,18439,77,18598,78,18759,76,18919,76,19080,75,19239,75,19400,74,19561,1,19563,70,19725,1,19730,62,19895,2,19898,54,20060,2,20063,48,20228,1,20230,41,20393,1,20396,1,20398,33,20561,29,20727,2,20731,18,20893,1,20896,13,21061,7,21225,1]" Type="3" Size="3" Color="0" Angle="6" /></Layout></Component><Component id="1" name="In"><Layout name="In_Center_Single" Number="0" Position="[[0.5, 0.5, 0.33, 0.33]]" Uniformity="3"><Entity bbox="[0.5, 0.5, 0.33, 0.33]" real_bbox="[0.5, 0.5, 0.1838, 0.1838]" mask="[10638,7,10796,11,10953,17,11112,19,11272,19,11430,23,11589,25,11749,25,11909,25,12068,27,12228,27,12387,29,12547,29,12707,29,12867,29,13027,29,13187,29,13347,29,13508,27,13668,27,13829,25,13989,25,14149,25,14310,23,14472,19,14632,19,14793,17,14956,11,15118,7]" Type="5" Size="1" Color="0" Angle="5" /></Layout></Component></Struct></Panel><Panel><Struct name="Out_In"><Component id="0" name="Out"><Layout name="Out_Center_Single" Number="0" Position="[[0.5, 0.5, 1, 1]]" Uniformity="0"><Entity bbox="[0.5, 0.5, 1, 1]" real_bbox="[0.4801, 0.5199, 0.7568, 0.7568]" mask="[2650,1,2808,5,2967,7,3125,10,3282,14,3441,16,3599,19,3756,23,3914,26,4071,1,4073,28,4230,32,4388,35,4547,37,4705,40,4862,1,4864,42,5021,46,5179,49,5336,1,5338,51,5495,55,5653,58,5811,61,5970,63,6127,67,6285,70,6442,1,6444,72,6601,76,6759,79,6916,1,6918,81,7075,85,7233,88,7391,91,7548,1,7550,93,7707,97,7865,100,8024,102,8183,104,8343,105,8503,106,8664,106,8824,107,8984,108,9144,109,9304,110,9465,110,9625,111,9784,113,9945,113,10105,114,10265,115,10426,115,10585,117,10745,118,10906,118,11066,119,11226,119,11386,120,11546,119,11706,119,11867,117,12027,116,12187,116,12347,115,12507,115,12667,115,12828,113,12987,113,13147,113,13308,111,13468,111,13628,111,13788,110,13948,110,14109,108,14269,107,14429,108,14589,107,14749,106,14909,106,15069,105,15230,103,15390,103,15549,103,15710,101,15870,102,16030,101,16190,100,16350,100,16511,98,16671,97,16831,98,16991,97,17151,96,17312,95,17471,95,17632,94,17792,93,17951,93,18112,92,18272,92,18432,91,18593,90,18752,90,18913,88,19073,89,19233,88,19393,87,19553,87,19714,85,19874,84,20034,85,20194,84,20355,82,20519,78,20684,1,20686,70,20849,1,20852,1,20854,62,21019,56,21184,1,21187,47,21354,41,21519,2,21522,32,21688,25,21854,2,21857,16,22020,1,22023,9,22188,3]" Type="3" Size="4" Color="0" Angle="6" /></Layout></Component><Component id="1" name="In"><Layout name="In_Center_Single" Number="0" Position="[[0.5, 0.5, 0.33, 0.33]]" Uniformity="3"><Entity bbox="[0.5, 0.5, 0.33, 0.33]" real_bbox="[0.5, 0.5, 0.1838, 0.1838]" mask="[10638,7,10796,11,10953,17,11112,19,11272,19,11430,23,11589,25,11749,25,11909,25,12068,27,12228,27,12387,29,12547,29,12707,29,12867,29,13027,29,13187,29,13347,29,13508,27,13668,27,13829,25,13989,25,14149,25,14310,23,14472,19,14632,19,14793,17,14956,11,15118,7]" Type="5" Size="1" Color="0" Angle="5" /></Layout></Component></Struct></Panel><Panel><Struct name="Out_In"><Component id="0" name="Out"><Layout name="Out_Center_Single" Number="0" Position="[[0.5, 0.5, 1, 1]]" Uniformity="0"><Entity bbox="[0.5, 0.5, 1, 1]" real_bbox="[0.4801, 0.5199, 0.7568, 0.7568]" mask="[2650,1,2808,5,2967,7,3125,10,3282,14,3441,16,3599,19,3756,23,3914,26,4071,1,4073,28,4230,32,4388,35,4547,37,4705,40,4862,1,4864,42,5021,46,5179,49,5336,1,5338,51,5495,55,5653,58,5811,61,5970,63,6127,67,6285,70,6442,1,6444,72,6601,76,6759,79,6916,1,6918,81,7075,85,7233,88,7391,91,7548,1,7550,93,7707,97,7865,100,8024,102,8183,104,8343,105,8503,106,8664,106,8824,107,8984,108,9144,109,9304,110,9465,110,9625,111,9784,113,9945,113,10105,114,10265,115,10426,115,10585,117,10745,118,10906,118,11066,119,11226,119,11386,120,11546,119,11706,119,11867,117,12027,116,12187,116,12347,115,12507,115,12667,115,12828,113,12987,113,13147,113,13308,111,13468,111,13628,111,13788,110,13948,110,14109,108,14269,107,14429,108,14589,107,14749,106,14909,106,15069,105,15230,103,15390,103,15549,103,15710,101,15870,102,16030,101,16190,100,16350,100,16511,98,16671,97,16831,98,16991,97,17151,96,17312,95,17471,95,17632,94,17792,93,17951,93,18112,92,18272,92,18432,91,18593,90,18752,90,18913,88,19073,89,19233,88,19393,87,19553,87,19714,85,19874,84,20034,85,20194,84,20355,82,20519,78,20684,1,20686,70,20849,1,20852,1,20854,62,21019,56,21184,1,21187,47,21354,41,21519,2,21522,32,21688,25,21854,2,21857,16,22020,1,22023,9,22188,3]" Type="3" Size="4" Color="0" Angle="6" /></Layout></Component><Component id="1" name="In"><Layout name="In_Center_Single" Number="0" Position="[[0.5, 0.5, 0.33, 0.33]]" Uniformity="3"><Entity bbox="[0.5, 0.5, 0.33, 0.33]" real_bbox="[0.5, 0.4781, 0.1562, 0.1375]" mask="[10966,2,11124,5,11282,7,11441,8,11599,10,11757,12,11916,13,12074,15,12232,17,12390,19,12549,20,12707,22,12867,22,13027,22,13189,20,13350,19,13512,17,13674,15,13836,13,13997,12,14159,10,14321,8,14482,7,14644,5,14806,2]" Type="1" Size="1" Color="0" Angle="5" /></Layout></Component></Struct></Panel><Panel><Struct name="Out_In"><Component id="0" name="Out"><Layout name="Out_Center_Single" Number="0" Position="[[0.5, 0.5, 1, 1]]" Uniformity="0"><Entity bbox="[0.5, 0.5, 1, 1]" real_bbox="[0.4801, 0.5199, 0.7568, 0.7568]" mask="[2650,1,2808,5,2967,7,3125,10,3282,14,3441,16,3599,19,3756,23,3914,26,4071,1,4073,28,4230,32,4388,35,4547,37,4705,40,4862,1,4864,42,5021,46,5179,49,5336,1,5338,51,5495,55,5653,58,5811,61,5970,63,6127,67,6285,70,6442,1,6444,72,6601,76,6759,79,6916,1,6918,81,7075,85,7233,88,7391,91,7548,1,7550,93,7707,97,7865,100,8024,102,8183,104,8343,105,8503,106,8664,106,8824,107,8984,108,9144,109,9304,110,9465,110,9625,111,9784,113,9945,113,10105,114,10265,115,10426,115,10585,117,10745,118,10906,118,11066,119,11226,119,11386,120,11546,119,11706,119,11867,117,12027,116,12187,116,12347,115,12507,115,12667,115,12828,113,12987,113,13147,113,13308,111,13468,111,13628,111,13788,110,13948,110,14109,108,14269,107,14429,108,14589,107,14749,106,14909,106,15069,105,15230,103,15390,103,15549,103,15710,101,15870,102,16030,101,16190,100,16350,100,16511,98,16671,97,16831,98,16991,97,17151,96,17312,95,17471,95,17632,94,17792,93,17951,93,18112,92,18272,92,18432,91,18593,90,18752,90,18913,88,19073,89,19233,88,19393,87,19553,87,19714,85,19874,84,20034,85,20194,84,20355,82,20519,78,20684,1,20686,70,20849,1,20852,1,20854,62,21019,56,21184,1,21187,47,21354,41,21519,2,21522,32,21688,25,21854,2,21857,16,22020,1,22023,9,22188,3]" Type="3" Size="4" Color="0" Angle="6" /></Layout></Component><Component id="1" name="In"><Layout name="In_Center_Single" Number="0" Position="[[0.5, 0.5, 0.33, 0.33]]" Uniformity="3"><Entity bbox="[0.5, 0.5, 0.33, 0.33]" real_bbox="[0.5, 0.5, 0.2828, 0.2828]" mask="[9357,9,9513,17,9671,20,9829,25,9988,27,10146,30,10305,33,10465,33,10624,35,10783,37,10943,37,11102,39,11262,39,11421,41,11580,43,11740,43,11900,43,12060,43,12219,45,12379,45,12539,45,12699,45,12859,45,13019,45,13179,45,13339,45,13499,45,13660,43,13820,43,13980,43,14140,43,14301,41,14461,41,14622,39,14782,39,14943,37,15104,35,15264,35,15425,33,15586,30,15748,27,15909,25,16071,20,16233,17,16397,9]" Type="5" Size="4" Color="0" Angle="5" /></Layout></Component></Struct></Panel><Panel><Struct name="Out_In"><Component id="0" name="Out"><Layout name="Out_Center_Single" Number="0" Position="[[0.5, 0.5, 1, 1]]" Uniformity="0"><Entity bbox="[0.5, 0.5, 1, 1]" real_bbox="[0.4801, 0.5199, 0.7568, 0.7568]" mask="[2650,1,2808,5,2967,7,3125,10,3282,14,3441,16,3599,19,3756,23,3914,26,4071,1,4073,28,4230,32,4388,35,4547,37,4705,40,4862,1,4864,42,5021,46,5179,49,5336,1,5338,51,5495,55,5653,58,5811,61,5970,63,6127,67,6285,70,6442,1,6444,72,6601,76,6759,79,6916,1,6918,81,7075,85,7233,88,7391,91,7548,1,7550,93,7707,97,7865,100,8024,102,8183,104,8343,105,8503,106,8664,106,8824,107,8984,108,9144,109,9304,110,9465,110,9625,111,9784,113,9945,113,10105,114,10265,115,10426,115,10585,117,10745,118,10906,118,11066,119,11226,119,11386,120,11546,119,11706,119,11867,117,12027,116,12187,116,12347,115,12507,115,12667,115,12828,113,12987,113,13147,113,13308,111,13468,111,13628,111,13788,110,13948,110,14109,108,14269,107,14429,108,14589,107,14749,106,14909,106,15069,105,15230,103,15390,103,15549,103,15710,101,15870,102,16030,101,16190,100,16350,100,16511,98,16671,97,16831,98,16991,97,17151,96,17312,95,17471,95,17632,94,17792,93,17951,93,18112,92,18272,92,18432,91,18593,90,18752,90,18913,88,19073,89,19233,88,19393,87,19553,87,19714,85,19874,84,20034,85,20194,84,20355,82,20519,78,20684,1,20686,70,20849,1,20852,1,20854,62,21019,56,21184,1,21187,47,21354,41,21519,2,21522,32,21688,25,21854,2,21857,16,22020,1,22023,9,22188,3]" Type="3" Size="4" Color="0" Angle="6" /></Layout></Component><Component id="1" name="In"><Layout name="In_Center_Single" Number="0" Position="[[0.5, 0.5, 0.33, 0.33]]" Uniformity="3"><Entity bbox="[0.5, 0.5, 0.33, 0.33]" real_bbox="[0.5, 0.5, 0.2498, 0.2498]" mask="[9837,9,9994,15,10152,19,10310,23,10469,25,10628,27,10787,29,10946,31,11105,33,11265,33,11424,35,11584,35,11743,37,11903,37,12063,37,12223,37,12382,39,12542,39,12702,39,12862,39,13022,39,13182,39,13342,39,13502,39,13663,37,13823,37,13983,37,14144,35,14304,35,14465,33,14625,33,14786,31,14947,29,15108,27,15269,25,15430,23,15592,19,15754,15,15917,9]" Type="5" Size="3" Color="0" Angle="5" /></Layout></Component></Struct></Panel><Panel><Struct name="Out_In"><Component id="0" name="Out"><Layout name="Out_Center_Single" Number="0" Position="[[0.5, 0.5, 1, 1]]" Uniformity="0"><Entity bbox="[0.5, 0.5, 1, 1]" real_bbox="[0.4801, 0.5199, 0.7568, 0.7568]" mask="[2650,1,2808,5,2967,7,3125,10,3282,14,3441,16,3599,19,3756,23,3914,26,4071,1,4073,28,4230,32,4388,35,4547,37,4705,40,4862,1,4864,42,5021,46,5179,49,5336,1,5338,51,5495,55,5653,58,5811,61,5970,63,6127,67,6285,70,6442,1,6444,72,6601,76,6759,79,6916,1,6918,81,7075,85,7233,88,7391,91,7548,1,7550,93,7707,97,7865,100,8024,102,8183,104,8343,105,8503,106,8664,106,8824,107,8984,108,9144,109,9304,110,9465,110,9625,111,9784,113,9945,113,10105,114,10265,115,10426,115,10585,117,10745,118,10906,118,11066,119,11226,119,11386,120,11546,119,11706,119,11867,117,12027,116,12187,116,12347,115,12507,115,12667,115,12828,113,12987,113,13147,113,13308,111,13468,111,13628,111,13788,110,13948,110,14109,108,14269,107,14429,108,14589,107,14749,106,14909,106,15069,105,15230,103,15390,103,15549,103,15710,101,15870,102,16030,101,16190,100,16350,100,16511,98,16671,97,16831,98,16991,97,17151,96,17312,95,17471,95,17632,94,17792,93,17951,93,18112,92,18272,92,18432,91,18593,90,18752,90,18913,88,19073,89,19233,88,19393,87,19553,87,19714,85,19874,84,20034,85,20194,84,20355,82,20519,78,20684,1,20686,70,20849,1,20852,1,20854,62,21019,56,21184,1,21187,47,21354,41,21519,2,21522,32,21688,25,21854,2,21857,16,22020,1,22023,9,22188,3]" Type="3" Size="4" Color="0" Angle="6" /></Layout></Component><Component id="1" name="In"><Layout name="In_Center_Single" Number="0" Position="[[0.5, 0.5, 0.33, 0.33]]" Uniformity="3"><Entity bbox="[0.5, 0.5, 0.33, 0.33]" real_bbox="[0.5, 0.4906, 0.1687, 0.1625]" mask="[10796,3,10955,7,11115,9,11274,13,11433,17,11592,20,11752,21,11911,22,12070,23,12229,24,12389,24,12548,25,12707,26,12867,26,13027,26,13188,25,13349,24,13509,24,13670,23,13831,22,13992,21,14152,20,14313,17,14474,13,14635,9,14795,7,14956,3]" Type="3" Size="1" Color="0" Angle="5" /></Layout></Component></Struct></Panel><Panel><Struct name="Out_In"><Component id="0" name="Out"><Layout name="Out_Center_Single" Number="0" Position="[[0.5, 0.5, 1, 1]]" Uniformity="0"><Entity bbox="[0.5, 0.5, 1, 1]" real_bbox="[0.4801, 0.5199, 0.7568, 0.7568]" mask="[2650,1,2808,5,2967,7,3125,10,3282,14,3441,16,3599,19,3756,23,3914,26,4071,1,4073,28,4230,32,4388,35,4547,37,4705,40,4862,1,4864,42,5021,46,5179,49,5336,1,5338,51,5495,55,5653,58,5811,61,5970,63,6127,67,6285,70,6442,1,6444,72,6601,76,6759,79,6916,1,6918,81,7075,85,7233,88,7391,91,7548,1,7550,93,7707,97,7865,100,8024,102,8183,104,8343,105,8503,106,8664,106,8824,107,8984,108,9144,109,9304,110,9465,110,9625,111,9784,113,9945,113,10105,114,10265,115,10426,115,10585,117,10745,118,10906,118,11066,119,11226,119,11386,120,11546,119,11706,119,11867,117,12027,116,12187,116,12347,115,12507,115,12667,115,12828,113,12987,113,13147,113,13308,111,13468,111,13628,111,13788,110,13948,110,14109,108,14269,107,14429,108,14589,107,14749,106,14909,106,15069,105,15230,103,15390,103,15549,103,15710,101,15870,102,16030,101,16190,100,16350,100,16511,98,16671,97,16831,98,16991,97,17151,96,17312,95,17471,95,17632,94,17792,93,17951,93,18112,92,18272,92,18432,91,18593,90,18752,90,18913,88,19073,89,19233,88,19393,87,19553,87,19714,85,19874,84,20034,85,20194,84,20355,82,20519,78,20684,1,20686,70,20849,1,20852,1,20854,62,21019,56,21184,1,21187,47,21354,41,21519,2,21522,32,21688,25,21854,2,21857,16,22020,1,22023,9,22188,3]" Type="3" Size="4" Color="0" Angle="6" /></Layout></Component><Component id="1" name="In"><Layout name="In_Center_Single" Number="0" Position="[[0.5, 0.5, 0.33, 0.33]]" Uniformity="3"><Entity bbox="[0.5, 0.5, 0.33, 0.33]" real_bbox="[0.5, 0.5, 0.1508, 0.1508]" mask="[11118,7,11276,11,11434,15,11593,17,11752,19,11912,19,12071,21,12231,21,12390,23,12550,23,12710,23,12870,23,13030,23,13190,23,13350,23,13511,21,13672,19,13832,19,13992,19,14153,17,14314,15,14476,11,14638,7]" Type="5" Size="0" Color="0" Angle="5" /></Layout></Component></Struct></Panel></Panels><Rules><Rule_Group id="0"><Rule name="Constant" attr="Number/Position" /><Rule name="Constant" attr="Type" /><Rule name="Distribute_Three" attr="Size" /><Rule name="Constant" attr="Color" /></Rule_Group><Rule_Group id="1"><Rule name="Constant" attr="Number/Position" /><Rule name="Progression" attr="Type" /><Rule name="Progression" attr="Size" /><Rule name="Constant" attr="Color" /></Rule_Group></Rules></Data>