<Data><Panels><Panel><Struct name="Singleton"><Component id="0" name="Grid"><Layout name="Distribute_Four" Number="1" Position="[[0.25, 0.25, 0.5, 0.5], [0.25, 0.75, 0.5, 0.5], [0.75, 0.25, 0.5, 0.5], [0.75, 0.75, 0.5, 0.5]]" Uniformity="1"><Entity bbox="[0.25, 0.75, 0.5, 0.5]" real_bbox="[0.2456, 0.7544, 0.1955, 0.1955]" mask="[3962,3,4120,6,4277,10,4435,13,4592,17,4751,19,4907,24,5066,26,5225,28,5386,28,5546,29,5707,29,5866,31,6026,32,6187,31,6346,32,6506,31,6667,30,6827,29,6987,29,7147,29,7307,28,7467,28,7627,27,7788,26,7948,26,8107,26,8268,24,8428,24,8589,23,8751,1,8754,18,8921,2,8924,2,8927,4,9089,1]" Type="3" Size="0" Color="1" Angle="6" /><Entity bbox="[0.75, 0.75, 0.5, 0.5]" real_bbox="[0.75, 0.7375, 0.2062, 0.1937]" mask="[16756,3,16915,6,17075,9,17234,13,17393,16,17552,20,17711,23,17871,24,18030,25,18189,26,18348,27,18507,28,18667,28,18826,29,18985,30,19144,31,19304,31,19464,31,19625,30,19786,29,19947,28,20107,28,20268,27,20429,26,20590,25,20751,24,20911,23,21072,20,21233,16,21394,13,21555,9,21715,6,21876,3]" Type="3" Size="0" Color="1" Angle="5" /></Layout></Component></Struct></Panel><Panel><Struct name="Singleton"><Component id="0" name="Grid"><Layout name="Distribute_Four" Number="2" Position="[[0.25, 0.25, 0.5, 0.5], [0.25, 0.75, 0.5, 0.5], [0.75, 0.25, 0.5, 0.5], [0.75, 0.75, 0.5, 0.5]]" Uniformity="1"><Entity bbox="[0.75, 0.75, 0.5, 0.5]" real_bbox="[0.725, 0.75, 0.1688, 0.1813]" mask="[16601,1,16760,3,16920,3,17079,5,17238,7,17398,7,17557,9,17717,9,17876,11,18036,11,18195,13,18355,13,18514,15,18674,15,18833,17,18993,17,19152,19,19311,21,19471,21,19630,23,19790,23,19949,25,20109,25,20268,27,20428,27,20587,29,20748,27]" Type="1" Size="0" Color="6" Angle="3" /><Entity bbox="[0.25, 0.75, 0.5, 0.5]" real_bbox="[0.261, 0.761, 0.1823, 0.1823]" mask="[4429,2,4588,7,4748,11,4909,12,5069,15,5229,17,5247,2,5389,22,5550,24,5710,28,5870,28,6030,28,6191,27,6351,26,6512,24,6672,23,6832,22,6993,20,7153,19,7314,17,7473,17,7633,16,7794,14,7954,13,8115,11,8275,10,8435,9,8596,7,8756,6,8916,5,9076,4]" Type="1" Size="0" Color="6" Angle="4" /><Entity bbox="[0.75, 0.25, 0.5, 0.5]" real_bbox="[0.761, 0.261, 0.1823, 0.1823]" mask="[17149,2,17308,7,17468,11,17629,12,17789,15,17949,17,17967,2,18109,22,18270,24,18430,28,18590,28,18750,28,18911,27,19071,26,19232,24,19392,23,19552,22,19713,20,19873,19,20034,17,20193,17,20353,16,20514,14,20674,13,20835,11,20995,10,21155,9,21316,7,21476,6,21636,5,21796,4]" Type="1" Size="0" Color="6" Angle="4" /></Layout></Component></Struct></Panel><Panel><Struct name="Singleton"><Component id="0" name="Grid"><Layout name="Distribute_Four" Number="2" Position="[[0.25, 0.25, 0.5, 0.5], [0.25, 0.75, 0.5, 0.5], [0.75, 0.25, 0.5, 0.5], [0.75, 0.75, 0.5, 0.5]]" Uniformity="1"><Entity bbox="[0.25, 0.75, 0.5, 0.5]" real_bbox="[0.25, 0.75, 0.2688, 0.2688]" mask="[2999,5,3005,1,3154,1,3156,11,3168,1,3312,19,3469,1,3471,21,3493,1,3628,27,3787,29,3946,31,4105,33,4264,35,4423,37,4582,39,4743,37,4902,39,5061,41,5221,41,5380,43,5541,41,5700,43,5859,44,6020,43,6179,45,6339,45,6499,45,6659,45,6819,45,6980,43,7139,44,7300,43,7461,41,7620,43,7781,41,7941,41,8102,39,8263,37,8422,39,8583,37,8744,35,8905,33,9066,31,9227,29,9388,27,9549,1,9551,21,9573,1,9712,19,9874,1,9876,11,9888,1,10039,5,10045,1]" Type="5" Size="1" Color="7" Angle="0" /><Entity bbox="[0.75, 0.25, 0.5, 0.5]" real_bbox="[0.75, 0.25, 0.2688, 0.2688]" mask="[15877,9,16034,15,16192,19,16349,24,16509,25,16667,29,16826,31,16985,33,17145,33,17303,37,17463,37,17623,37,17782,39,17942,39,18101,41,18261,41,18421,41,18580,43,18740,43,18900,43,19060,43,19220,43,19380,43,19540,43,19700,43,19860,43,20021,41,20181,41,20341,41,20502,39,20662,39,20823,37,20983,37,21144,35,21305,33,21465,33,21626,31,21787,29,21949,25,22109,24,22272,19,22434,15,22597,9]" Type="5" Size="1" Color="7" Angle="7" /><Entity bbox="[0.75, 0.75, 0.5, 0.5]" real_bbox="[0.75, 0.75, 0.2688, 0.2688]" mask="[15957,9,16114,15,16272,19,16429,24,16589,25,16747,29,16906,31,17065,33,17225,33,17383,37,17543,37,17703,37,17862,39,18022,39,18181,41,18341,41,18501,41,18660,43,18820,43,18980,43,19140,43,19300,43,19460,43,19620,43,19780,43,19940,43,20101,41,20261,41,20421,41,20582,39,20742,39,20903,37,21063,37,21224,35,21385,33,21545,33,21706,31,21867,29,22029,25,22189,24,22352,19,22514,15,22677,9]" Type="5" Size="1" Color="7" Angle="7" /></Layout></Component></Struct></Panel><Panel><Struct name="Singleton"><Component id="0" name="Grid"><Layout name="Distribute_Four" Number="2" Position="[[0.25, 0.25, 0.5, 0.5], [0.25, 0.75, 0.5, 0.5], [0.75, 0.25, 0.5, 0.5], [0.75, 0.75, 0.5, 0.5]]" Uniformity="1"><Entity bbox="[0.25, 0.75, 0.5, 0.5]" real_bbox="[0.25, 0.7188, 0.2312, 0.2062]" mask="[3651,1,3809,4,3967,6,4126,7,4284,9,4442,11,4600,13,4758,15,4917,16,5075,18,5233,20,5391,22,5550,23,5708,25,5866,27,6024,29,6183,30,6341,32,6500,33,6661,32,6823,30,6984,29,7146,27,7308,25,7470,23,7631,22,7793,20,7955,18,8117,16,8278,15,8440,13,8602,11,8764,9,8926,7,9087,6,9249,4,9411,1]" Type="1" Size="1" Color="3" Angle="5" /><Entity bbox="[0.75, 0.25, 0.5, 0.5]" real_bbox="[0.75, 0.2812, 0.2312, 0.2062]" mask="[16351,1,16510,4,16670,6,16830,7,16990,9,17150,11,17310,13,17470,15,17630,16,17790,18,17950,20,18110,22,18270,23,18430,25,18590,27,18750,29,18910,30,19070,32,19230,33,19390,32,19550,30,19710,29,19870,27,20030,25,20190,23,20350,22,20510,20,20670,18,20830,16,20990,15,21150,13,21310,11,21470,9,21630,7,21790,6,21950,4,22111,1]" Type="1" Size="1" Color="3" Angle="1" /><Entity bbox="[0.25, 0.25, 0.5, 0.5]" real_bbox="[0.2188, 0.25, 0.2062, 0.2312]" mask="[3081,1,3240,3,3400,3,3559,5,3718,7,3878,7,4037,9,4197,9,4356,11,4516,11,4675,13,4834,15,4994,15,5153,17,5313,17,5472,19,5632,19,5791,21,5950,23,6110,23,6269,25,6429,25,6588,27,6748,27,6907,29,7067,29,7226,31,7385,33,7545,33,7704,35,7864,35,8023,37,8184,35]" Type="1" Size="1" Color="3" Angle="3" /></Layout></Component></Struct></Panel><Panel><Struct name="Singleton"><Component id="0" name="Grid"><Layout name="Distribute_Four" Number="1" Position="[[0.25, 0.25, 0.5, 0.5], [0.25, 0.75, 0.5, 0.5], [0.75, 0.25, 0.5, 0.5], [0.75, 0.75, 0.5, 0.5]]" Uniformity="1"><Entity bbox="[0.75, 0.25, 0.5, 0.5]" real_bbox="[0.75, 0.25, 0.2688, 0.2688]" mask="[15877,9,16034,15,16192,19,16350,24,16509,25,16667,29,16826,31,16985,33,17145,33,17303,37,17463,37,17623,37,17782,39,17942,39,18101,41,18261,41,18421,41,18580,43,18740,43,18900,43,19060,43,19220,43,19380,43,19540,43,19700,43,19860,43,20021,41,20181,41,20341,41,20502,39,20662,39,20823,37,20983,37,21144,35,21305,33,21465,33,21626,31,21787,29,21949,25,22110,24,22272,19,22434,15,22597,9]" Type="5" Size="1" Color="6" Angle="5" /><Entity bbox="[0.75, 0.75, 0.5, 0.5]" real_bbox="[0.75, 0.75, 0.2688, 0.2688]" mask="[15797,1,15799,5,15954,1,15956,11,15968,1,16112,19,16269,1,16271,21,16293,1,16428,27,16587,29,16746,31,16905,33,17064,35,17223,37,17382,39,17543,37,17702,39,17861,41,18021,41,18180,43,18341,41,18500,43,18660,44,18820,43,18979,45,19139,45,19299,45,19459,45,19619,45,19780,43,19940,44,20100,43,20261,41,20420,43,20581,41,20741,41,20902,39,21063,37,21222,39,21383,37,21544,35,21705,33,21866,31,22027,29,22188,27,22349,1,22351,21,22373,1,22512,19,22674,1,22676,11,22688,1,22837,1,22839,5]" Type="5" Size="1" Color="6" Angle="4" /></Layout></Component></Struct></Panel><Panel><Struct name="Singleton"><Component id="0" name="Grid"><Layout name="Distribute_Four" Number="3" Position="[[0.25, 0.25, 0.5, 0.5], [0.25, 0.75, 0.5, 0.5], [0.75, 0.25, 0.5, 0.5], [0.75, 0.75, 0.5, 0.5]]" Uniformity="1"><Entity bbox="[0.25, 0.25, 0.5, 0.5]" real_bbox="[0.2412, 0.2588, 0.3369, 0.3369]" mask="[1964,3,2122,6,2279,10,2437,13,2596,15,2753,19,2911,22,3070,24,3228,27,3385,31,3544,33,3702,36,3859,40,4017,43,4176,45,4335,47,4495,48,4655,49,4816,49,4976,50,5136,51,5296,52,5456,53,5617,53,5776,54,5936,54,6097,52,6256,53,6417,51,6577,51,6737,51,6897,50,7057,50,7217,49,7378,47,7538,47,7698,47,7858,46,8018,46,8179,44,8338,44,8499,43,8659,42,8818,43,8979,42,9139,41,9299,40,9460,39,9619,39,9780,38,9941,1,9943,35,10106,1,10109,1,10111,26,10276,21,10442,1,10444,2,10447,9,10612,3]" Type="3" Size="3" Color="9" Angle="6" /><Entity bbox="[0.25, 0.75, 0.5, 0.5]" real_bbox="[0.2412, 0.7412, 0.3369, 0.3369]" mask="[2036,3,2195,6,2354,10,2513,13,2672,15,2831,19,2990,22,3149,24,3308,27,3467,31,3626,33,3785,36,3944,40,4103,43,4262,45,4421,47,4580,48,4739,49,4898,49,5057,50,5216,51,5375,52,5534,53,5693,53,5853,54,6013,54,6174,52,6334,53,6495,51,6655,51,6815,51,6976,50,7136,50,7297,49,7458,47,7618,47,7778,47,7939,46,8099,46,8260,44,8421,44,8581,43,8742,42,8902,43,9062,42,9223,41,9384,40,9544,39,9705,39,9865,38,10025,35,10061,1,10186,26,10213,1,10216,1,10346,21,10507,9,10517,2,10520,1,10668,3]" Type="3" Size="3" Color="9" Angle="0" /><Entity bbox="[0.75, 0.25, 0.5, 0.5]" real_bbox="[0.7688, 0.25, 0.3312, 0.3437]" mask="[15545,33,15704,35,15864,35,16023,37,16183,37,16343,37,16502,39,16662,39,16822,39,16981,41,17141,41,17301,41,17460,43,17620,43,17780,43,17939,45,18099,45,18259,45,18418,47,18578,47,18738,47,18897,49,19057,49,19217,49,19376,51,19536,51,19696,51,19855,53,20015,53,20175,53,20334,55,20494,55,20654,55,20815,53,20977,49,21138,47,21299,45,21461,41,21622,39,21783,37,21945,33,22106,31,22267,29,22428,27,22590,23,22751,21,22912,19,23074,15,23235,13,23396,11,23558,7,23719,5,23880,3]" Type="3" Size="3" Color="9" Angle="7" /><Entity bbox="[0.75, 0.75, 0.5, 0.5]" real_bbox="[0.7588, 0.7588, 0.3369, 0.3369]" mask="[15172,3,15322,1,15324,2,15327,9,15476,21,15626,1,15629,1,15631,26,15781,1,15783,35,15940,38,16099,39,16260,39,16419,40,16579,41,16739,42,16898,43,17059,42,17219,43,17378,44,17539,44,17698,46,17858,46,18018,47,18178,47,18338,47,18497,49,18657,50,18817,50,18977,51,19137,51,19297,51,19456,53,19617,52,19776,54,19936,54,20097,53,20256,53,20416,52,20576,51,20736,50,20896,49,21055,49,21215,48,21375,47,21536,45,21697,43,21859,40,22022,36,22184,33,22345,31,22508,27,22670,24,22831,22,22993,19,23156,15,23317,13,23479,10,23642,6,23804,3]" Type="3" Size="3" Color="9" Angle="4" /></Layout></Component></Struct></Panel><Panel><Struct name="Singleton"><Component id="0" name="Grid"><Layout name="Distribute_Four" Number="1" Position="[[0.25, 0.25, 0.5, 0.5], [0.25, 0.75, 0.5, 0.5], [0.75, 0.25, 0.5, 0.5], [0.75, 0.75, 0.5, 0.5]]" Uniformity="1"><Entity bbox="[0.75, 0.75, 0.5, 0.5]" real_bbox="[0.75, 0.75, 0.2688, 0.2688]" mask="[15797,1,15799,5,15805,1,15954,1,15956,11,15968,1,16112,19,16269,1,16271,21,16293,1,16428,27,16587,29,16746,31,16905,33,17064,35,17223,37,17382,39,17543,37,17702,39,17861,41,18021,41,18180,43,18341,41,18500,43,18660,43,18820,43,18979,45,19139,45,19299,45,19459,45,19619,45,19780,43,19939,45,20100,43,20261,41,20420,43,20581,41,20741,41,20902,39,21063,37,21222,39,21383,37,21544,35,21705,33,21866,31,22027,29,22188,27,22349,1,22351,21,22373,1,22512,19,22674,1,22676,11,22688,1,22839,5]" Type="5" Size="1" Color="2" Angle="6" /><Entity bbox="[0.25, 0.75, 0.5, 0.5]" real_bbox="[0.25, 0.75, 0.2688, 0.2688]" mask="[2999,5,3005,1,3154,1,3156,11,3168,1,3312,19,3469,1,3471,21,3493,1,3628,27,3787,29,3946,31,4105,33,4264,35,4423,37,4582,39,4743,37,4902,39,5061,41,5221,41,5380,43,5541,41,5700,43,5859,44,6020,43,6179,45,6339,45,6499,45,6659,45,6819,45,6980,43,7139,44,7300,43,7461,41,7620,43,7781,41,7941,41,8102,39,8263,37,8422,39,8583,37,8744,35,8905,33,9066,31,9227,29,9388,27,9549,1,9551,21,9573,1,9712,19,9874,1,9876,11,9888,1,10039,5,10045,1]" Type="5" Size="1" Color="2" Angle="0" /></Layout></Component></Struct></Panel><Panel><Struct name="Singleton"><Component id="0" name="Grid"><Layout name="Distribute_Four" Number="2" Position="[[0.25, 0.25, 0.5, 0.5], [0.25, 0.75, 0.5, 0.5], [0.75, 0.25, 0.5, 0.5], [0.75, 0.75, 0.5, 0.5]]" Uniformity="1"><Entity bbox="[0.25, 0.25, 0.5, 0.5]" real_bbox="[0.2588, 0.2588, 0.2928, 0.2928]" mask="[2770,1,2925,1,2927,6,3074,1,3078,16,3229,2,3232,22,3384,31,3543,33,3702,34,3862,35,4022,36,4182,35,4342,36,4501,38,4661,39,4822,38,4981,40,5141,40,5300,41,5461,41,5621,41,5781,42,5940,44,6100,44,6260,45,6420,46,6580,46,6740,46,6900,47,7059,48,7220,46,7379,46,7539,45,7699,44,7858,44,8019,42,8179,41,8340,39,8502,36,8663,34,8825,31,8986,1,8988,27,9149,25,9310,23,9472,20,9635,16,9797,13,9958,11,10120,8,10281,6,10444,2]" Type="3" Size="2" Color="3" Angle="4" /><Entity bbox="[0.75, 0.75, 0.5, 0.5]" real_bbox="[0.75, 0.7656, 0.2938, 0.2875]" mask="[15647,3,15804,7,15961,10,16117,15,16274,19,16431,23,16588,26,16744,31,16902,34,17061,36,17221,37,17381,37,17541,38,17701,39,17861,40,18021,40,18181,41,18341,42,18501,43,18661,43,18821,44,18981,45,19141,46,19301,46,19461,46,19621,45,19781,44,19941,43,20101,43,20261,42,20421,41,20581,40,20741,40,20901,39,21061,38,21221,37,21381,37,21541,36,21702,34,21864,31,22028,26,22191,23,22354,19,22517,15,22681,10,22844,7,23007,3]" Type="3" Size="2" Color="3" Angle="1" /><Entity bbox="[0.75, 0.25, 0.5, 0.5]" real_bbox="[0.75, 0.2344, 0.2937, 0.2875]" mask="[15553,3,15712,7,15872,10,16031,15,16190,19,16349,23,16509,26,16668,31,16827,34,16986,36,17145,37,17305,37,17464,38,17623,39,17782,40,17942,40,18101,41,18260,42,18419,43,18579,43,18738,44,18897,45,19056,46,19216,46,19376,46,19537,45,19698,44,19859,43,20019,43,20180,42,20341,41,20502,40,20662,40,20823,39,20984,38,21145,37,21305,37,21466,36,21627,34,21788,31,21949,26,22109,23,22270,19,22431,15,22592,10,22752,7,22913,3]" Type="3" Size="2" Color="3" Angle="5" /></Layout></Component></Struct></Panel><Panel><Struct name="Singleton"><Component id="0" name="Grid"><Layout name="Distribute_Four" Number="0" Position="[[0.25, 0.25, 0.5, 0.5], [0.25, 0.75, 0.5, 0.5], [0.75, 0.25, 0.5, 0.5], [0.75, 0.75, 0.5, 0.5]]" Uniformity="1"><Entity bbox="[0.25, 0.75, 0.5, 0.5]" real_bbox="[0.25, 0.75, 0.2132, 0.2132]" mask="[3800,1,3802,1,3959,5,4118,7,4277,9,4436,11,4595,13,4754,15,4913,17,5072,19,5231,21,5390,23,5549,25,5708,27,5867,29,6026,31,6185,33,6344,35,6505,33,6664,35,6825,33,6986,31,7147,29,7308,27,7469,25,7630,23,7791,21,7952,19,8113,17,8274,15,8435,13,8596,11,8757,9,8918,7,9079,5,9240,1,9242,1]" Type="2" Size="0" Color="7" Angle="0" /></Layout></Component></Struct></Panel><Panel><Struct name="Singleton"><Component id="0" name="Grid"><Layout name="Distribute_Four" Number="3" Position="[[0.25, 0.25, 0.5, 0.5], [0.25, 0.75, 0.5, 0.5], [0.75, 0.25, 0.5, 0.5], [0.75, 0.75, 0.5, 0.5]]" Uniformity="1"><Entity bbox="[0.25, 0.25, 0.5, 0.5]" real_bbox="[0.25, 0.2938, 0.3188, 0.2812]" mask="[2427,1,2586,4,2746,6,2906,7,3066,9,3226,11,3386,13,3546,14,3706,16,3866,18,4026,20,4186,21,4346,23,4506,25,4666,27,4826,28,4986,30,5146,32,5306,34,5466,35,5626,37,5786,39,5946,41,6106,42,6266,44,6426,45,6586,44,6746,42,6906,41,7066,39,7226,37,7386,35,7546,34,7706,32,7866,30,8026,28,8186,27,8346,25,8506,23,8666,21,8826,20,8986,18,9146,16,9306,14,9466,13,9626,11,9786,9,9946,7,10106,6,10266,4,10427,1]" Type="1" Size="3" Color="5" Angle="1" /><Entity bbox="[0.25, 0.75, 0.5, 0.5]" real_bbox="[0.2812, 0.75, 0.2062, 0.2312]" mask="[4744,35,4903,37,5064,35,5224,35,5385,33,5545,33,5706,31,5867,29,6027,29,6188,27,6348,27,6509,25,6669,25,6830,23,6990,23,7151,21,7312,19,7472,19,7633,17,7793,17,7954,15,8114,15,8275,13,8436,11,8596,11,8757,9,8917,9,9078,7,9238,7,9399,5,9560,3,9720,3,9881,1]" Type="1" Size="1" Color="5" Angle="7" /><Entity bbox="[0.75, 0.25, 0.5, 0.5]" real_bbox="[0.775, 0.25, 0.1688, 0.1812]" mask="[17788,27,17947,29,18108,27,18268,27,18429,25,18589,25,18750,23,18910,23,19071,21,19231,21,19392,19,19553,17,19713,17,19874,15,20034,15,20195,13,20355,13,20516,11,20676,11,20837,9,20997,9,21158,7,21318,7,21479,5,21640,3,21800,3,21961,1]" Type="1" Size="0" Color="5" Angle="7" /><Entity bbox="[0.75, 0.75, 0.5, 0.5]" real_bbox="[0.75, 0.7875, 0.2688, 0.2437]" mask="[15949,1,16108,4,16268,6,16428,8,16588,9,16748,11,16908,13,17068,15,17228,17,17388,18,17548,20,17708,22,17868,24,18028,26,18188,27,18348,29,18508,31,18668,33,18828,35,18988,36,19148,38,19308,39,19468,38,19628,36,19788,35,19948,33,20108,31,20268,29,20428,27,20588,26,20748,24,20908,22,21068,20,21228,18,21388,17,21548,15,21708,13,21868,11,22028,9,22188,8,22348,6,22508,4,22669,1]" Type="1" Size="2" Color="5" Angle="1" /></Layout></Component></Struct></Panel><Panel><Struct name="Singleton"><Component id="0" name="Grid"><Layout name="Distribute_Four" Number="3" Position="[[0.25, 0.25, 0.5, 0.5], [0.25, 0.75, 0.5, 0.5], [0.75, 0.25, 0.5, 0.5], [0.75, 0.75, 0.5, 0.5]]" Uniformity="1"><Entity bbox="[0.25, 0.25, 0.5, 0.5]" real_bbox="[0.25, 0.25, 0.2938, 0.2938]" mask="[2739,45,2898,47,3058,47,3218,47,3378,47,3538,47,3698,47,3858,47,4018,47,4178,47,4338,47,4498,47,4658,47,4818,47,4978,47,5138,47,5298,47,5458,47,5618,47,5778,47,5938,47,6098,47,6258,47,6418,47,6578,47,6738,47,6898,47,7058,47,7218,47,7378,47,7538,47,7698,47,7858,47,8018,47,8178,47,8338,47,8498,47,8658,47,8818,47,8978,47,9138,47,9298,47,9458,47,9618,47,9778,47,9938,47,10099,45]" Type="2" Size="4" Color="5" Angle="1" /><Entity bbox="[0.25, 0.75, 0.5, 0.5]" real_bbox="[0.2719, 0.75, 0.375, 0.3938]" mask="[2343,37,2502,39,2662,39,2821,41,2981,41,3141,41,3300,43,3460,43,3620,43,3779,45,3939,45,4099,45,4258,47,4418,47,4577,49,4737,49,4897,49,5056,51,5216,51,5376,51,5535,53,5695,53,5855,53,6014,55,6174,55,6334,55,6493,57,6653,57,6813,57,6972,59,7132,59,7291,61,7451,61,7611,61,7770,63,7930,63,8090,63,8251,61,8413,57,8574,55,8735,53,8897,49,9058,47,9219,45,9381,41,9542,39,9703,37,9864,35,10026,31,10187,29,10348,27,10510,23,10671,21,10832,19,10994,15,11155,13,11316,11,11478,7,11639,5,11800,3]" Type="3" Size="4" Color="5" Angle="7" /><Entity bbox="[0.75, 0.25, 0.5, 0.5]" real_bbox="[0.75, 0.25, 0.4188, 0.4188]" mask="[13955,13,14111,20,14269,25,14427,29,14584,35,14743,37,14902,39,15060,43,15219,45,15378,47,15537,49,15696,51,15855,53,16015,53,16174,55,16333,57,16492,59,16652,59,16812,59,16971,61,17131,61,17290,63,17450,63,17609,65,17769,65,17929,65,18089,65,18248,67,18408,67,18568,67,18728,67,18888,67,19048,67,19208,67,19368,67,19528,67,19688,67,19848,67,20008,67,20168,67,20329,65,20489,65,20649,65,20810,63,20970,63,21130,63,21291,61,21451,61,21612,59,21772,59,21932,59,22093,57,22254,55,22415,53,22575,53,22736,51,22897,49,23058,47,23219,45,23380,43,23542,39,23703,37,23864,35,24027,29,24189,25,24351,20,24515,13]" Type="5" Size="4" Color="5" Angle="7" /><Entity bbox="[0.75, 0.75, 0.5, 0.5]" real_bbox="[0.75, 0.7719, 0.3938, 0.375]" mask="[14369,3,14526,7,14684,9,14841,13,14998,17,15155,21,15312,24,15469,28,15627,31,15784,35,15941,38,16098,42,16256,45,16415,47,16575,48,16735,48,16895,49,17055,50,17215,51,17375,51,17535,52,17695,53,17855,54,18015,54,18175,55,18335,56,18495,57,18655,57,18815,58,18975,59,19135,60,19295,60,19455,60,19615,59,19775,58,19935,57,20095,57,20255,56,20415,55,20575,54,20735,54,20895,53,21055,52,21215,51,21375,51,21535,50,21695,49,21855,48,22015,48,22175,47,22336,45,22498,42,22661,38,22824,35,22987,31,23149,28,23312,24,23475,21,23638,17,23801,13,23964,9,24126,7,24289,3]" Type="3" Size="4" Color="5" Angle="1" /></Layout></Component></Struct></Panel><Panel><Struct name="Singleton"><Component id="0" name="Grid"><Layout name="Distribute_Four" Number="0" Position="[[0.25, 0.25, 0.5, 0.5], [0.25, 0.75, 0.5, 0.5], [0.75, 0.25, 0.5, 0.5], [0.75, 0.75, 0.5, 0.5]]" Uniformity="1"><Entity bbox="[0.75, 0.75, 0.5, 0.5]" real_bbox="[0.75, 0.75, 0.3016, 0.3016]" mask="[15480,3,15639,5,15798,7,15957,9,16116,11,16275,13,16434,15,16593,17,16752,19,16911,21,17070,23,17229,25,17388,27,17547,29,17706,31,17865,33,18024,35,18183,37,18342,39,18501,41,18660,43,18819,45,18978,47,19137,49,19297,49,19457,49,19618,47,19779,45,19940,43,20101,41,20262,39,20423,37,20584,35,20745,33,20906,31,21067,29,21228,27,21389,25,21550,23,21711,21,21872,19,22033,17,22194,15,22355,13,22516,11,22677,9,22838,7,22999,5,23160,3]" Type="2" Size="2" Color="4" Angle="4" /></Layout></Component></Struct></Panel><Panel><Struct name="Singleton"><Component id="0" name="Grid"><Layout name="Distribute_Four" Number="3" Position="[[0.25, 0.25, 0.5, 0.5], [0.25, 0.75, 0.5, 0.5], [0.75, 0.25, 0.5, 0.5], [0.75, 0.75, 0.5, 0.5]]" Uniformity="1"><Entity bbox="[0.25, 0.25, 0.5, 0.5]" real_bbox="[0.25, 0.2719, 0.3938, 0.375]" mask="[1489,3,1646,7,1804,9,1961,13,2118,17,2275,21,2432,24,2589,28,2747,31,2904,35,3061,38,3218,42,3376,45,3535,47,3695,48,3855,48,4015,49,4175,50,4335,51,4495,51,4655,52,4815,53,4975,54,5135,54,5295,55,5455,56,5615,57,5775,57,5935,58,6095,59,6255,60,6415,60,6575,60,6735,59,6895,58,7055,57,7215,57,7375,56,7535,55,7695,54,7855,54,8015,53,8175,52,8335,51,8495,51,8655,50,8815,49,8975,48,9135,48,9295,47,9456,45,9618,42,9781,38,9944,35,10107,31,10269,28,10432,24,10595,21,10758,17,10921,13,11084,9,11246,7,11409,3]" Type="3" Size="4" Color="5" Angle="1" /><Entity bbox="[0.25, 0.75, 0.5, 0.5]" real_bbox="[0.25, 0.75, 0.4188, 0.3562]" mask="[1240,3,1398,7,1557,9,1715,13,1873,17,2031,21,2190,23,2348,27,2506,31,2665,33,2823,37,2981,41,3140,43,3298,47,3456,51,3615,53,3773,57,3933,57,4093,57,4253,57,4413,57,4573,57,4733,57,4893,57,5053,57,5213,57,5373,57,5533,57,5693,57,5853,57,6013,57,6173,57,6333,57,6493,57,6653,57,6813,57,6973,57,7133,57,7293,57,7453,57,7613,57,7773,57,7933,57,8093,57,8253,57,8413,57,8573,57,8733,57,8893,57,9053,57,9213,57,9375,53,9536,51,9698,47,9860,43,10021,41,10183,37,10345,33,10506,31,10668,27,10830,23,10991,21,11153,17,11315,13,11477,9,11638,7,11800,3]" Type="4" Size="4" Color="5" Angle="7" /><Entity bbox="[0.75, 0.25, 0.5, 0.5]" real_bbox="[0.7719, 0.25, 0.375, 0.3938]" mask="[15063,37,15222,39,15382,39,15541,41,15701,41,15861,41,16020,43,16180,43,16340,43,16499,45,16659,45,16819,45,16978,47,17138,47,17297,49,17457,49,17617,49,17776,51,17936,51,18096,51,18255,53,18415,53,18575,53,18734,55,18894,55,19054,55,19213,57,19373,57,19533,57,19692,59,19852,59,20011,61,20171,61,20331,61,20490,63,20650,63,20810,63,20971,61,21133,57,21294,55,21455,53,21617,49,21778,47,21939,45,22101,41,22262,39,22423,37,22584,35,22746,31,22907,29,23068,27,23230,23,23391,21,23552,19,23714,15,23875,13,24036,11,24198,7,24359,5,24520,3]" Type="3" Size="4" Color="5" Angle="7" /><Entity bbox="[0.75, 0.75, 0.5, 0.5]" real_bbox="[0.75, 0.75, 0.4188, 0.4188]" mask="[14035,13,14191,20,14349,25,14507,29,14664,35,14823,37,14982,39,15140,43,15299,45,15458,47,15617,49,15776,51,15935,53,16095,53,16254,55,16413,57,16572,59,16732,59,16892,59,17051,61,17211,61,17370,63,17530,63,17690,63,17849,65,18009,65,18169,65,18328,67,18488,67,18648,67,18808,67,18968,67,19128,67,19288,67,19448,67,19608,67,19768,67,19928,67,20088,67,20248,67,20409,65,20569,65,20729,65,20889,65,21050,63,21210,63,21371,61,21531,61,21692,59,21852,59,22012,59,22173,57,22334,55,22495,53,22655,53,22816,51,22977,49,23138,47,23299,45,23460,43,23622,39,23783,37,23944,35,24107,29,24269,25,24431,20,24595,13]" Type="5" Size="4" Color="5" Angle="1" /></Layout></Component></Struct></Panel><Panel><Struct name="Singleton"><Component id="0" name="Grid"><Layout name="Distribute_Four" Number="3" Position="[[0.25, 0.25, 0.5, 0.5], [0.25, 0.75, 0.5, 0.5], [0.75, 0.25, 0.5, 0.5], [0.75, 0.75, 0.5, 0.5]]" Uniformity="1"><Entity bbox="[0.25, 0.25, 0.5, 0.5]" real_bbox="[0.25, 0.25, 0.4188, 0.4188]" mask="[1155,13,1311,20,1469,25,1627,29,1784,35,1943,37,2102,39,2260,43,2419,45,2578,47,2737,49,2896,51,3055,53,3215,53,3374,55,3533,57,3692,59,3852,59,4012,59,4171,61,4331,61,4490,63,4650,63,4810,63,4969,65,5129,65,5289,65,5448,67,5608,67,5768,67,5928,67,6088,67,6248,67,6408,67,6568,67,6728,67,6888,67,7048,67,7208,67,7368,67,7529,65,7689,65,7849,65,8009,65,8170,63,8330,63,8491,61,8651,61,8812,59,8972,59,9132,59,9293,57,9454,55,9615,53,9775,53,9936,51,10097,49,10258,47,10419,45,10580,43,10742,39,10903,37,11064,35,11227,29,11389,25,11551,20,11715,13]" Type="5" Size="4" Color="5" Angle="1" /><Entity bbox="[0.25, 0.75, 0.5, 0.5]" real_bbox="[0.25, 0.75, 0.4188, 0.4188]" mask="[1235,13,1391,20,1549,25,1707,29,1864,35,2023,37,2182,39,2340,43,2499,45,2658,47,2817,49,2976,51,3135,53,3295,53,3454,55,3613,57,3772,59,3932,59,4092,59,4251,61,4411,61,4570,63,4730,63,4889,65,5049,65,5209,65,5369,65,5528,67,5688,67,5848,67,6008,67,6168,67,6328,67,6488,67,6648,67,6808,67,6968,67,7128,67,7288,67,7448,67,7609,65,7769,65,7929,65,8090,63,8250,63,8410,63,8571,61,8731,61,8892,59,9052,59,9212,59,9373,57,9534,55,9695,53,9855,53,10016,51,10177,49,10338,47,10499,45,10660,43,10822,39,10983,37,11144,35,11307,29,11469,25,11631,20,11795,13]" Type="5" Size="4" Color="5" Angle="7" /><Entity bbox="[0.75, 0.25, 0.5, 0.5]" real_bbox="[0.75, 0.25, 0.2937, 0.2938]" mask="[15539,45,15698,47,15858,47,16018,47,16178,47,16338,47,16498,47,16658,47,16818,47,16978,47,17138,47,17298,47,17458,47,17618,47,17778,47,17938,47,18098,47,18258,47,18418,47,18578,47,18738,47,18898,47,19058,47,19218,47,19378,47,19538,47,19698,47,19858,47,20018,47,20178,47,20338,47,20498,47,20658,47,20818,47,20978,47,21138,47,21298,47,21458,47,21618,47,21778,47,21938,47,22098,47,22258,47,22418,47,22578,47,22738,47,22899,45]" Type="2" Size="4" Color="5" Angle="7" /><Entity bbox="[0.75, 0.75, 0.5, 0.5]" real_bbox="[0.75, 0.75, 0.3562, 0.4187]" mask="[14824,35,14984,35,15143,37,15302,39,15462,39,15621,41,15781,41,15940,43,16099,45,16259,45,16418,47,16578,47,16737,49,16896,51,17056,51,17215,53,17375,53,17534,55,17693,57,17853,57,18012,59,18172,59,18331,61,18491,61,18650,63,18809,65,18969,65,19128,67,19288,67,19448,67,19609,65,19769,65,19930,63,20091,61,20251,61,20412,59,20572,59,20733,57,20893,57,21054,55,21215,53,21375,53,21536,51,21696,51,21857,49,22018,47,22178,47,22339,45,22499,45,22660,43,22821,41,22981,41,23142,39,23302,39,23463,37,23624,35,23784,35]" Type="4" Size="4" Color="5" Angle="1" /></Layout></Component></Struct></Panel><Panel><Struct name="Singleton"><Component id="0" name="Grid"><Layout name="Distribute_Four" Number="3" Position="[[0.25, 0.25, 0.5, 0.5], [0.25, 0.75, 0.5, 0.5], [0.75, 0.25, 0.5, 0.5], [0.75, 0.75, 0.5, 0.5]]" Uniformity="1"><Entity bbox="[0.25, 0.25, 0.5, 0.5]" real_bbox="[0.25, 0.3, 0.3562, 0.3188]" mask="[1945,1,2104,4,2264,6,2424,7,2584,9,2744,11,2904,13,3064,15,3224,16,3384,18,3544,20,3704,22,3864,23,4024,25,4184,27,4344,29,4504,31,4664,32,4824,34,4984,36,5144,38,5304,39,5464,41,5624,43,5784,45,5944,47,6104,48,6264,50,6424,51,6584,50,6744,48,6904,47,7064,45,7224,43,7384,41,7544,39,7704,38,7864,36,8024,34,8184,32,8344,31,8504,29,8664,27,8824,25,8984,23,9144,22,9304,20,9464,18,9624,16,9784,15,9944,13,10104,11,10264,9,10424,7,10584,6,10744,4,10905,1]" Type="1" Size="4" Color="5" Angle="1" /><Entity bbox="[0.25, 0.75, 0.5, 0.5]" real_bbox="[0.3, 0.75, 0.3188, 0.3562]" mask="[3774,55,3933,57,4094,55,4254,55,4415,53,4575,53,4736,51,4897,49,5057,49,5218,47,5378,47,5539,45,5699,45,5860,43,6020,43,6181,41,6342,39,6502,39,6663,37,6823,37,6984,35,7144,35,7305,33,7466,31,7626,31,7787,29,7947,29,8108,27,8268,27,8429,25,8589,25,8750,23,8911,21,9071,21,9232,19,9392,19,9553,17,9713,17,9874,15,10035,13,10195,13,10356,11,10516,11,10677,9,10837,9,10998,7,11158,7,11319,5,11480,3,11640,3,11801,1]" Type="1" Size="4" Color="5" Angle="7" /><Entity bbox="[0.75, 0.25, 0.5, 0.5]" real_bbox="[0.8, 0.25, 0.3187, 0.3562]" mask="[16494,55,16653,57,16814,55,16974,55,17135,53,17295,53,17456,51,17617,49,17777,49,17938,47,18098,47,18259,45,18419,45,18580,43,18740,43,18901,41,19062,39,19222,39,19383,37,19543,37,19704,35,19864,35,20025,33,20186,31,20346,31,20507,29,20667,29,20828,27,20988,27,21149,25,21309,25,21470,23,21631,21,21791,21,21952,19,22112,19,22273,17,22433,17,22594,15,22755,13,22915,13,23076,11,23236,11,23397,9,23557,9,23718,7,23878,7,24039,5,24200,3,24360,3,24521,1]" Type="1" Size="4" Color="5" Angle="7" /><Entity bbox="[0.75, 0.75, 0.5, 0.5]" real_bbox="[0.75, 0.8, 0.3562, 0.3187]" mask="[14825,1,14984,4,15144,6,15304,7,15464,9,15624,11,15784,13,15944,15,16104,16,16264,18,16424,20,16584,22,16744,23,16904,25,17064,27,17224,29,17384,31,17544,32,17704,34,17864,36,18024,38,18184,39,18344,41,18504,43,18664,45,18824,47,18984,48,19144,50,19304,51,19464,50,19624,48,19784,47,19944,45,20104,43,20264,41,20424,39,20584,38,20744,36,20904,34,21064,32,21224,31,21384,29,21544,27,21704,25,21864,23,22024,22,22184,20,22344,18,22504,16,22664,15,22824,13,22984,11,23144,9,23304,7,23464,6,23624,4,23785,1]" Type="1" Size="4" Color="5" Angle="1" /></Layout></Component></Struct></Panel><Panel><Struct name="Singleton"><Component id="0" name="Grid"><Layout name="Distribute_Four" Number="3" Position="[[0.25, 0.25, 0.5, 0.5], [0.25, 0.75, 0.5, 0.5], [0.75, 0.25, 0.5, 0.5], [0.75, 0.75, 0.5, 0.5]]" Uniformity="1"><Entity bbox="[0.25, 0.25, 0.5, 0.5]" real_bbox="[0.25, 0.25, 0.3562, 0.4188]" mask="[1944,35,2104,35,2263,37,2422,39,2582,39,2741,41,2901,41,3060,43,3219,45,3379,45,3538,47,3698,47,3857,49,4016,51,4176,51,4335,53,4495,53,4654,55,4813,57,4973,57,5132,59,5292,59,5451,61,5611,61,5770,63,5929,65,6089,65,6248,67,6408,67,6568,67,6729,65,6889,65,7050,63,7211,61,7371,61,7532,59,7692,59,7853,57,8013,57,8174,55,8335,53,8495,53,8656,51,8816,51,8977,49,9138,47,9298,47,9459,45,9619,45,9780,43,9941,41,10101,41,10262,39,10422,39,10583,37,10744,35,10904,35]" Type="4" Size="4" Color="5" Angle="1" /><Entity bbox="[0.25, 0.75, 0.5, 0.5]" real_bbox="[0.25, 0.75, 0.2938, 0.2937]" mask="[2819,45,2978,47,3138,47,3298,47,3458,47,3618,47,3778,47,3938,47,4098,47,4258,47,4418,47,4578,47,4738,47,4898,47,5058,47,5218,47,5378,47,5538,47,5698,47,5858,47,6018,47,6178,47,6338,47,6498,47,6658,47,6818,47,6978,47,7138,47,7298,47,7458,47,7618,47,7778,47,7938,47,8098,47,8258,47,8418,47,8578,47,8738,47,8898,47,9058,47,9218,47,9378,47,9538,47,9698,47,9858,47,10018,47,10179,45]" Type="2" Size="4" Color="5" Angle="7" /><Entity bbox="[0.75, 0.25, 0.5, 0.5]" real_bbox="[0.75, 0.25, 0.4187, 0.3562]" mask="[13960,3,14118,7,14277,9,14435,13,14593,17,14751,21,14910,23,15068,27,15226,31,15385,33,15543,37,15701,41,15860,43,16018,47,16176,51,16335,53,16493,57,16653,57,16813,57,16973,57,17133,57,17293,57,17453,57,17613,57,17773,57,17933,57,18093,57,18253,57,18413,57,18573,57,18733,57,18893,57,19053,57,19213,57,19373,57,19533,57,19693,57,19853,57,20013,57,20173,57,20333,57,20493,57,20653,57,20813,57,20973,57,21133,57,21293,57,21453,57,21613,57,21773,57,21933,57,22095,53,22256,51,22418,47,22580,43,22741,41,22903,37,23065,33,23226,31,23388,27,23550,23,23711,21,23873,17,24035,13,24197,9,24358,7,24520,3]" Type="4" Size="4" Color="5" Angle="7" /><Entity bbox="[0.75, 0.75, 0.5, 0.5]" real_bbox="[0.75, 0.75, 0.2938, 0.2937]" mask="[15619,45,15778,47,15938,47,16098,47,16258,47,16418,47,16578,47,16738,47,16898,47,17058,47,17218,47,17378,47,17538,47,17698,47,17858,47,18018,47,18178,47,18338,47,18498,47,18658,47,18818,47,18978,47,19138,47,19298,47,19458,47,19618,47,19778,47,19938,47,20098,47,20258,47,20418,47,20578,47,20738,47,20898,47,21058,47,21218,47,21378,47,21538,47,21698,47,21858,47,22018,47,22178,47,22338,47,22498,47,22658,47,22818,47,22979,45]" Type="2" Size="4" Color="5" Angle="1" /></Layout></Component></Struct></Panel></Panels><Rules><Rule_Group id="0"><Rule name="Arithmetic" attr="Position" /><Rule name="Distribute_Three" attr="Type" /><Rule name="Arithmetic" attr="Size" /><Rule name="Arithmetic" attr="Color" /></Rule_Group></Rules></Data>